Workbook
Name aff: 'QuickVal Proforma'!#REF!
Name Units: 'QuickVal Proforma'!$C$12

Sheet Validation Lists | Graph Values
A1: MSA Options | B1: County Options | C1: Type | D1: Brokerage Options | F1: Qualifier | G1: Cap Rate
A2: Anaheim-Santa Ana-Irvine | B2: Arapahoe | C2: Garden / tbd | D2: Berkadia | F2: =CONCATENATE('QuickVal Proforma'!F4,'QuickVal Proforma'!G4) -> T12/T12 Actual | G2: ='QuickVal Proforma'!F5 -> 0
A3: Atlanta | B3: Arlington | C3: Garden / Wood | D3: C&W | F3: ='QuickVal Proforma'!I4 -> <--- RET & OpEx adj. | G3: ='QuickVal Proforma'!I5 -> #DIV/0!
A4: Austin | B4: Bergen | C4: Garden / Concrete | D4: CBRE | F4: ='QuickVal Proforma'!L4 -> <--- w/ Revenue Losses stblz. | G4: ='QuickVal Proforma'!L5 -> #DIV/0!
A5: Baltimore | B5: Broward | C5: Garden / Steel | D5: Eastdil | F5: ='QuickVal Proforma'!O4 -> Untrended Stablized | G5: ='QuickVal Proforma'!O5 -> #DIV/0!
A6: Boston | B6: Charleston | C6: Garden HD / tbd | D6: Engler | F6: ='QuickVal Proforma'!B29 -> Exit Cap Rate | G6: ='QuickVal Proforma'!C29 -> 0.0525
A7: Boulder | B7: Chester | C7: Garden HD / Wood | D7: IPA
A8: Bridgeport-Stamford | B8: Clark | C8: Garden HD / Concrete | D8: JLL
A9: Charleston | B9: Cobb | C9: Garden HD / Steel | D9: Newmark
A10: Charlotte | B10: Collin | C10: Mid-Rise Wrap / tbd | D10: Northmarq
A11: Chicago | B11: Cook | C11: Mid-Rise Wrap / Wood | D11: W&D
A12: Dallas-Plano-Irving | B12: Dallas | C12: Mid-Rise Wrap / Concrete | D12: W&D / Engler
A13: Denver | B13: Davidson | C13: Mid-Rise Wrap / Steel | D13: none
A14: Ft. Lauderdale-Pompano | B14: DeKalb | C14: Mid-Rise Podium / tbd | D14: BlueGate
A15: Ft. Worth-Arlington | B15: Denton | C15: Mid-Rise Podium / Wood | D15: Patterson
A16: Greenville | B16: Denver | C16: Mid-Rise Podium / Concrete | D16: Colliers
A17: Houston | B17: Douglas | C17: Mid-Rise Podium / Steel | D17: Bravo & Partners
A18: Jacksonville | B18: DuPage | C18: High-Rise / tbd
A19: L.A. - Long Beach-Glendale | B19: Durham | C19: High-Rise / Wood
A20: Las Vegas | B20: Durham/Orange | C20: High-Rise / Concrete
A21: Miami-Kendall | B21: Forsyth | C21: High-Rise / Steel
A22: Minneapolis-St. Paul | B22: Fulton | C22: Other
A23: N. Port-Sarasota-Bradenton | B23: Gwinnett
A24: Naples-Marco Island | B24: Harris
A25: Nashville | B25: Hennepin
A26: Nassau Co. - Suffolk Co. | B26: Hillsborough
A27: New York-White Plains | B27: Iredell
A28: Newark-Jersey City | B28: Jefferson
A29: Oakland-Hayward-Berkeley | B29: Kane
A30: Orlando | B30: King
A31: Oxnard-Thousand Oaks | B31: Los Angeles
A32: Palm Bay-Melbourne | B32: Manatee
A33: Philadelphia | B33: Maricopa
A34: Phoenix | B34: Marietta
... A52: Worcester | B52: Ventura
B53: Wake
B54: Williamson

Sheet QuickVal Proforma
B2: =CONCATENATE(C5," | ","Quick Valuation") -> | Quick Valuation
B3: =TODAY() -> 46136 | R3: 5
B4: Property Overview | F4: T12 | G4: /T12 Actual | I4: <--- RET & OpEx adj. | L4: <--- w/ Revenue Losses stblz. | O4: Untrended Stablized | R4: Trended Stablized | U4: Payroll Schedule | V4: Salary | W4: Head Count | X4: Total $s
B5: Property Name | F5: =F48/$C$23 -> 0 | I5: =I48/$C$23 -> #DIV/0! | L5: =L48/$C$23 -> #DIV/0! | O5: =O48/($C$27) -> #DIV/0! | R5: =R48/$C$27 -> #DIV/0! | U5: Manager | V5: 95000 | W5: 0 | X5: =V5*W5 -> 0
B6: Street Address | E6: RENTAL REVENUE | F6: =CONCATENATE(TEXT('T12 Intake'!O3, "[$-en-US]mmm-yy;@")," T12") -> Jul-25 T12 | G6: Per Unit | I6: RET & OpEx adj. | J6: Per Unit | L6: Stabilized Losses | M6: Per Unit | O6: Untrended | P6: Per Unit | R6: Trended | S6: Per Unit | U6: Assistant Manager | V6: 65000 | W6: 0 | X6: =V6*W6 -> 0
B7: City, State, ZIP | E7: Gross Potential Rent - Market Rate | F7: =HLOOKUP($F$4,'T12 Clean'!$O$4:$R$14,2,FALSE) -> 0 | G7: =IFERROR(F7/Units,0)/12 -> 0 | I7: =F7 -> 0 | J7: =IFERROR(I7/Units,0)/12 -> 0 | L7: =I7 -> 0 | M7: =L7/Units/12 -> #DIV/0! | O7: =L10*(1+$C$36)+(Y50*Y51*12) -> #DIV/0! | P7: =O7/Units/12 -> #DIV/0! | R7: =O7*(1+C35)^(R3-0.5) -> #DIV/0! | S7: =R7/Units/12 -> #DIV/0! | U7: Leasing - Staff | V7: 55000 | W7: 0 | X7: =V7*W7 -> 0
B8: MSA | E8: Gross Potential Rent - Affordables | F8: =HLOOKUP($F$4,'T12 Clean'!$O$4:$R$14,3,FALSE) -> 0 | G8: =IFERROR(F8/Units,0)/12 -> 0 | I8: =F8 -> 0 | J8: =IFERROR(I8/Units,0)/12 -> 0 | L8: =I8 -> 0 | M8: =L8/Units/12 -> #DIV/0! | O8: =L8*(1+$C$37) -> 0 | P8: =O8/Units/12 -> #DIV/0! | R8: =O8*(1+$C$37)^(R3-0.5) -> 0 | S8: =R8/Units/12 -> #DIV/0! | U8: Doorman | V8: 50000 | W8: 0 | X8: =V8*W8 -> 0
B9: County | E9: Gain / Loss-to-Lease | F9: =HLOOKUP($F$4,'T12 Clean'!$O$4:$R$14,4,FALSE) -> 0 | G9: =IFERROR(-F9/$F$7,0) -> 0 | I9: =F9 -> 0 | J9: =IFERROR(-I9/$I$7,0) -> 0 | L9: =I9 -> 0 | M9: =IFERROR(-L9/$L$7,0) -> 0 | O9: =O7*-P9 -> #DIV/0! | P9: =IF($C$36>2%,$C$36/2,1%) -> 0.01 | R9: =R7*-S9 -> #DIV/0! | S9: =P9 -> 0.01 | U9: Concierge | V9: 50000 | W9: 0 | X9: =V9*W9 -> 0
B10: Initial CFO Date | C10: =TODAY()+30 -> 46166 | E10: Net Potential Rent | F10: =SUM(F7:F9) -> 0 | G10: =IFERROR(F10/Units,0)/12 -> 0 | I10: =SUM(I7:I9) -> 0 | J10: =IFERROR(I10/Units,0)/12 -> 0 | L10: =SUM(L7:L9) -> 0 | M10: =L10/Units/12 -> #DIV/0! | O10: =SUM(O7:O9) -> #DIV/0! | P10: =O10/Units/12 -> #DIV/0! | R10: =SUM(R7:R9) -> #DIV/0! | S10: =R10/Units/12 -> #DIV/0! | U10: Maintenance - Manager | V10: 75000 | W10: 0 | X10: =V10*W10 -> 0
B11: Year of Constructon | E11: Physical Vacancy | F11: =HLOOKUP($F$4,'T12 Clean'!$O$4:$R$14,6,FALSE) -> 0 | G11: =IFERROR(-F11/SUM($F$7:$F$8),0) -> 0 | I11: =F11 -> 0 | J11: =IFERROR(-I11/SUM($I$7:$I$8),0) -> 0 | L11: =SUM($L$7:$L$8)*-M11 -> 0 | M11: 0.05 | O11: =SUM($O$7:$O$8)*-P11 -> #DIV/0! | P11: =M11 -> 0.05 | R11: =SUM($R$7:$R$8)*-S11 -> #DIV/0! | S11: =P11 -> 0.05 | U11: Maintenance - Tech | V11: 55000 | W11: 0 | X11: =V11*W11 -> 0
B12: Unit Count / Market Rate | E12: Concessions | F12: =HLOOKUP($F$4,'T12 Clean'!$O$4:$R$14,7,FALSE) -> 0 | G12: =IFERROR(-F12/$F$7,0) -> 0 | I12: =F12 -> 0 | J12: =IFERROR(-I12/$I$7,0) -> 0 | L12: =$L$7*-M12 -> 0 | M12: 0.001 | O12: =$O$7*-P12 -> #DIV/0! | P12: =M12 -> 0.001 | R12: =$R$7*-S12 -> #DIV/0! | S12: =P12 -> 0.001 | U12: Grounds | V12: 45000 | W12: 0 | X12: =V12*W12 -> 0
B13: Average Unit SF | C13: =259008/Units -> #DIV/0! | E13: Employee / Model Units | F13: =HLOOKUP($F$4,'T12 Clean'!$O$4:$R$14,8,FALSE) -> 0 | G13: =IFERROR(F13/-$F$7*Units,TEXT(0,"0.00")) -> 0.00 | I13: =F13 -> 0 | J13: =IFERROR(I13/-$I$7*Units,TEXT(0,"0.00")) -> 0.00 | L13: =$L$7/Units*-M13 -> #DIV/0! | M13: 1.25 | O13: =$O$7/Units*-P13 -> #DIV/0! | P13: =M13 -> 1.25 | R13: =$R$7/Units*-S13 -> #DIV/0! | S13: =P13 -> 1.25 | U13: Porter | V13: 35000 | W13: 0 | X13: =V13*W13 -> 0
B14: Parking Spaces | E14: Down Units | F14: =HLOOKUP($F$4,'T12 Clean'!$O$4:$R$14,9,FALSE) -> 0 | G14: =IFERROR(F14/-$F$7*Units,TEXT(0,"0.00")) -> 0.00 | I14: =F14 -> 0 | J14: =IFERROR(I14/-$I$7*Units,TEXT(0,"0.00")) -> 0.00 | L14: =$L$7/Units*-M14 -> #DIV/0! | M14: 0 | O14: =$O$7/Units*-P14 -> #DIV/0! | P14: =M14 -> 0 | R14: =$R$7/Units*-S14 -> #DIV/0! | S14: =P14 -> 0 | U14: Courtesy Patrol | V14: 50000 | W14: 0 | X14: =V14*W14 -> 0
B15: Property Type / Materials | E15: Bad Debt / Write-Offs | F15: =HLOOKUP($F$4,'T12 Clean'!$O$4:$R$14,10,FALSE) -> 0 | G15: =IFERROR(-F15/$F$7,0) -> 0 | I15: =F15 -> 0 | J15: =IFERROR(-I15/$I$7,0) -> 0 | L15: =$L$7*-M15 -> #DIV/0! | M15: =1/Units -> #DIV/0! | O15: =$O$7*-P15 -> #DIV/0! | P15: =M15 -> #DIV/0! | R15: =$R$7*-S15 -> #DIV/0! | S15: =P15 -> #DIV/0! | U15: Subtotal | W15: =SUM(W5:W14) -> 0 | X15: =SUM(X5:X14) -> 0
B16: GP Owner | E16: Net Rental Income | F16: =SUM(F10:F15) -> 0 | G16: =IFERROR(F16/Units,0) -> 0 | I16: =SUM(I10:I15) -> 0 | J16: =IFERROR(I16/Units,0) -> 0 | L16: =SUM(L10:L15) -> #DIV/0! | M16: =L16/Units -> #DIV/0! | O16: =SUM(O10:O15) -> #DIV/0! | P16: =O16/Units -> #DIV/0! | R16: =SUM(R10:R15) -> #DIV/0! | S16: =R16/Units -> #DIV/0! | U16: Bonuses | W16: 0.12 | X16: =W16*X15 -> 0
B17: Broker | E17: OTHER INCOME | U17: Burden | W17: 0.28 | X17: =W17*SUM(X15:X16) -> 0
B18: Broker Contact | E18: Parking | F18: =IFERROR('T12 Clean'!O16,0) -> 0 | G18: =IFERROR(F18/Units,0) -> 0 | I18: =F18 -> 0 | J18: =IFERROR(I18/Units,0) -> 0 | L18: =I18 -> 0 | M18: =L18/Units -> #DIV/0! | O18: =C59 -> 0 | P18: =O18/Units -> #DIV/0! | R18: =O18*(1+$C$38)^($R$3-1) -> 0 | S18: =R18/Units -> #DIV/0! | U18: T12 + 2% | V18: =F34*(1+$C$40) -> 0 | W18: Grand Total | X18: =SUM(X15:X17) -> 0
E19: Storage | F19: =IFERROR('T12 Clean'!O17,0) -> 0 | G19: =IFERROR(F19/Units,0) -> 0 | I19: =F19 -> 0 | J19: =IFERROR(I19/Units,0) -> 0 | L19: =I19 -> 0 | M19: =L19/Units -> #DIV/0! | O19: =L19 -> 0 | P19: =O19/Units -> #DIV/0! | R19: =O19*(1+$C$38)^($R$3-1) -> 0 | S19: =R19/Units -> #DIV/0! | U19: Per unit | V19: =V18/Units -> #DIV/0! | W19: Per unit | X19: =X18/Units -> #DIV/0!
B20: Purchase Summary | E20: Pet Fees / Rent | F20: =IFERROR('T12 Clean'!O18,0) -> 0 | G20: =IFERROR(F20/Units,0) -> 0 | I20: =F20 -> 0 | J20: =IFERROR(I20/Units,0) -> 0 | L20: =I20 -> 0 | M20: =L20/Units -> #DIV/0! | O20: =L20 -> 0 | P20: =O20/Units -> #DIV/0! | R20: =O20*(1+$C$38)^($R$3-1) -> 0 | S20: =R20/Units -> #DIV/0!
B21: Whisper Price | E21: Cable / Internet | F21: =IFERROR('T12 Clean'!O19,0) -> 0 | G21: =IFERROR(F21/Units,0) -> 0 | I21: =F21 -> 0 | J21: =IFERROR(I21/Units,0) -> 0 | L21: =I21 -> 0 | M21: =L21/Units -> #DIV/0! | O21: =L21 -> 0 | P21: =O21/Units -> #DIV/0! | R21: =O21*(1+$C$38)^($R$3-1) -> 0 | S21: =R21/Units -> #DIV/0! | U21: Real Estate Tax Schedule
B22: Per Unit / Per SF | C22: =IF(C21=0,"",CONCATENATE("$",ROUND(C21/Units/1000,),"k / $",ROUND(C21/Units/$C$13,),)) | E22: Other Income Misc. | F22: =IFERROR('T12 Clean'!O20,0) -> 0 | G22: =IFERROR(F22/Units,0) -> 0 | I22: =F22 -> 0 | J22: =IFERROR(I22/Units,0) -> 0 | L22: =I22 -> 0 | M22: =L22/Units -> #DIV/0! | O22: =L22 -> 0 | P22: =O22/Units -> #DIV/0! | R22: =O22*(1+$C$38)^($R$3-1) -> 0 | S22: =R22/Units -> #DIV/0! | U22: Re-Assessment Year | V22: 2026 | X22: Trended Re-Assessed RET | Y22: =HLOOKUP(V22,V27:AB41,15) -> 2210740.3 | AA22: County: | AB22: =C9 -> 0
B23: =IF(C21>0,CONCATENATE("Purchase Price (",ROUND(C23/C21*100,1),"% whisp.)"),"Purchase Price") -> Purchase Price | C23: 100000000 | E23: Utility Reimbursements | F23: =IFERROR('T12 Clean'!O21,0) -> 0 | G23: =F23/F37 -> #DIV/0! | I23: =F23 -> 0 | J23: =I23/I37 -> #DIV/0! | L23: =I23 -> 0 | M23: =L23/L37 -> #DIV/0! | O23: =P23*O37 -> #DIV/0! | P23: =G23 -> #DIV/0! | R23: =S23*R37 -> #DIV/0! | S23: =P23 -> #DIV/0! | U23: Re-Assessment Year | V23: Countywide | X23: # Yrs to Untrend | Y23: 1 | AA23: City, State, Zip: | AB23: =C7 -> 0
B24: Per Unit / Per SF | C24: =IF(C23=0,"",CONCATENATE("$",ROUND(C23/Units/1000,),"k / $",ROUND(C23/Units/$C$13,),)) -> #DIV/0! | E24: Total Other Income | F24: =SUM(F18:F23) -> 0 | G24: =IFERROR(F24/Units,0) -> 0 | I24: =SUM(I18:I23) -> 0 | J24: =IFERROR(I24/Units,0) -> 0 | L24: =SUM(L18:L23) -> 0 | M24: =L24/Units -> #DIV/0! | O24: =SUM(O18:O23) -> #DIV/0! | P24: =O24/Units -> #DIV/0! | R24: =SUM(R18:R23) -> #DIV/0! | S24: =R24/Units -> #DIV/0! | U24: Closing Date | V24: =DATE(YEAR($C$10),MONTH($C$10),DAY($C$10)+74) -> 46240 | X24: Untrend Rate | Y24: 0.02
B25: Closing Costs (%) | C25: 0.004 | E25: Commercial Income | F25: =IFERROR('T12 Clean'!O23,0) -> 0 | G25: =IFERROR(F25/Units,0) -> 0 | I25: =F25 -> 0 | J25: =IFERROR(I25/Units,0) -> 0 | L25: =I25 -> 0 | M25: =L25/Units -> #DIV/0! | O25: =L25 -> 0 | P25: =O25/Units -> #DIV/0! | R25: =O25*(1+$C$38)^($R$3-1) -> 0 | S25: =R25/Units -> #DIV/0! | U25: YR1 Month End | V25: =EOMONTH(V24,11) -> 46599 | X25: Untrended Re-Assessed RET | Y25: =Y22/(1+Y24)^Y23 -> 2167392.5
B26: Financing Costs (%) | C26: 0.006 | E26: Effective Gross Income | F26: =SUM(F16,F24:F25) -> 0 | G26: =IFERROR(F26/Units,0) -> 0 | I26: =SUM(I16,I24:I25) -> 0 | J26: =IFERROR(I26/Units,0) -> 0 | L26: =SUM(L16,L24:L25) -> #DIV/0! | M26: =L26/Units -> #DIV/0! | O26: =SUM(O16,O24:O25) -> #DIV/0! | P26: =O26/Units -> #DIV/0! | R26: =SUM(R16,R24:R25) -> #DIV/0! | S26: =R26/Units -> #DIV/0!
B27: Total Capitalization | C27: =IFERROR(C23+(C23*C25)+(C23*C26)+W60,0) -> 0 | U27: RET Year | V27: 2024 | W27: =V27+1 -> 2025 | X27: =W27+1 -> 2026 | Y27: =X27+1 -> 2027 | Z27: =Y27+1 -> 2028 | AA27: =Z27+1 -> 2029 | AB27: =AA27+1 -> 2030 | AC27: =AB27+1 -> 2031 | AD27: =AC27+1 -> 2032 | ... AF27: =AE27+1 -> 2034
B28: Per Unit / Per SF | C28: =IF(C27=0,"",CONCATENATE("$",ROUND(C27/Units/1000,),"k / $",ROUND(C27/Units/$C$13,),)) | E28: VARIABLE OPERATING EXPENSES | F28: =F6 -> Jul-25 T12 | G28: =G6 -> Per Unit | I28: =I6 -> RET & OpEx adj. | J28: =J6 -> Per Unit | L28: =L6 -> Stabilized Losses | M28: =M6 -> Per Unit | O28: =O6 -> Untrended | R28: =R6 -> Trended | U28: Market Value Growth Rate | W28: 0.02 | X28: =W28 -> 0.02 | Y28: =X28 -> 0.02 | Z28: =Y28 -> 0.02 | AA28: =Z28 -> 0.02 | AB28: =AA28 -> 0.02 | AC28: =AB28 -> 0.02 | AD28: =AC28 -> 0.02 | AE28: =AD28 -> 0.02 | AF28: =AE28 -> 0.02
B29: Exit Cap Rate | C29: 0.0525 | E29: Advertising / Marketing | F29: =IFERROR('T12 Clean'!O27,0) -> 0 | G29: =IFERROR(F29/Units,0) -> 0 | I29: =J29*Units -> 0 | J29: =G29*(1+$C$40) -> 0 | L29: =I29 -> 0 | M29: =L29/Units -> #DIV/0! | O29: =L29 -> 0 | P29: =O29/Units -> #DIV/0! | R29: =O29*(1+$C$40)^($R$3-1) -> 0 | S29: =R29/Units -> #DIV/0! | U29: Full Market Value | V29: 90000000 | W29: 90000000 | X29: =IF($V$22=X27,$C$23,W29*(1+X28)) -> 100000000 | Y29: =IF($V$22=Y27,$C$23,X29*(1+Y28)) -> 102000000 | Z29: =IF($V$22=Z27,$C$23,Y29*(1+Z28)) -> 104040000 | AA29: =IF($V$22=AA27,$C$23,Z29*(1+AA28)) -> 106120800 | AB29: =IF($V$22=AB27,$C$23,AA29*(1+AB28)) -> 108243216 | AC29: =IF($V$22=AC27,$C$23,AB29*(1+AC28)) -> 1.1040808e+08 | AD29: =IF($V$22=AD27,$C$23,AC29*(1+AD28)) -> 1.1261624e+08 | AE29: =IF($V$22=AE27,$C$23,AD29*(1+AE28)) -> 1.1486857e+08 | AF29: =IF($V$22=AF27,$C$23,AE29*(1+AF28)) -> 1.1716594e+08
B30: Residual Sale Price | C30: =IFERROR((R46-(J47*(1+$C$40)^(R3-1))*Units)/C29,0) -> 0 | E30: Administrative | F30: =IFERROR('T12 Clean'!O28,0) -> 0 | G30: =IFERROR(F30/Units,0) -> 0 | I30: =J30*Units -> 0 | J30: =G30*(1+$C$40) -> 0 | L30: =I30 -> 0 | M30: =L30/Units -> #DIV/0! | O30: =L30 -> 0 | P30: =O30/Units -> #DIV/0! | R30: =O30*(1+$C$40)^($R$3-1) -> 0 | S30: =R30/Units -> #DIV/0! | U30: Re-Assessment Ratio | W30: 1 | X30: 1 | Y30: =X30 -> 1 | Z30: =Y30 -> 1 | AA30: =Z30 -> 1 | AB30: =AA30 -> 1 | AC30: =AB30 -> 1 | AD30: =AC30 -> 1 | AE30: =AD30 -> 1 | AF30: =AE30 -> 1
B31: Per Unit / Per SF | C31: =IF(C30=0,"",CONCATENATE("$",ROUND(C30/Units/1000,),"k / $",ROUND(C30/Units/$C$13,),)) | E31: Repairs & Maintenance | F31: =IFERROR('T12 Clean'!O29,0) -> 0 | G31: =IFERROR(F31/Units,0) -> 0 | I31: =J31*Units -> 0 | J31: =G31*(1+$C$40) -> 0 | L31: =I31 -> 0 | M31: =L31/Units -> #DIV/0! | O31: =L31 -> 0 | P31: =O31/Units -> #DIV/0! | R31: =O31*(1+$C$40)^($R$3-1) -> 0 | S31: =R31/Units -> #DIV/0! | U31: Assessed Value | V31: =V29 -> 90000000 | W31: =W29*W30 -> 90000000 | X31: =X29*X30 -> 100000000 | Y31: =Y29*Y30 -> 102000000 | Z31: =Z29*Z30 -> 104040000 | AA31: =AA29*AA30 -> 106120800 | AB31: =AB29*AB30 -> 108243216 | AC31: =AC29*AC30 -> 1.1040808e+08 | AD31: =AD29*AD30 -> 1.1261624e+08 | ... AF31: =AF29*AF30 -> 1.1716594e+08
B32: Annual Asset Appreciation | C32: =IFERROR(RATE(R3-1,0,-C27-W60,C30),0) -> 0 | E32: Contract Services | F32: =IFERROR('T12 Clean'!O30,0) -> 0 | G32: =IFERROR(F32/Units,0) -> 0 | I32: =J32*Units -> 0 | J32: =G32*(1+$C$40) -> 0 | L32: =I32 -> 0 | M32: =L32/Units -> #DIV/0! | O32: =L32 -> 0 | P32: =O32/Units -> #DIV/0! | R32: =O32*(1+$C$40)^($R$3-1) -> 0 | S32: =R32/Units -> #DIV/0! | U32: Assessment Ratio | V32: 1 | W32: =V32 -> 1 | X32: =W32 -> 1 | Y32: =X32 -> 1 | Z32: =Y32 -> 1 | AA32: =Z32 -> 1 | AB32: =AA32 -> 1 | AC32: =AB32 -> 1 | AD32: =AC32 -> 1 | ... AF32: =AE32 -> 1
E33: Turnover / Make Ready | F33: =IFERROR('T12 Clean'!O31,0) -> 0 | G33: =IFERROR(F33/Units,0) -> 0 | I33: =J33*Units -> 0 | J33: =G33*(1+$C$40) -> 0 | L33: =I33 -> 0 | M33: =L33/Units -> #DIV/0! | O33: =L33 -> 0 | P33: =O33/Units -> #DIV/0! | R33: =O33*(1+$C$40)^($R$3-1) -> 0 | S33: =R33/Units -> #DIV/0! | U33: Tax Value | V33: =V31*V32 -> 90000000 | W33: =W31*W32 -> 90000000 | X33: =X31*X32 -> 100000000 | Y33: =Y31*Y32 -> 102000000 | Z33: =Z31*Z32 -> 104040000 | AA33: =AA31*AA32 -> 106120800 | AB33: =AB31*AB32 -> 108243216 | AC33: =AC31*AC32 -> 1.1040808e+08 | ... AF33: =AF31*AF32 -> 1.1716594e+08
B34: Proforma Assumptions | E34: Payroll & Benefits | F34: =IFERROR('T12 Clean'!O32,0) -> 0 | G34: =IFERROR(F34/Units,0) -> 0 | I34: =J34*Units -> #DIV/0! | J34: =IF(X19>0,X19,V19) -> #DIV/0! | L34: =I34 -> #DIV/0! | M34: =L34/Units -> #DIV/0! | O34: =L34 -> #DIV/0! | P34: =O34/Units -> #DIV/0! | R34: =O34*(1+$C$40)^($R$3-1) -> #DIV/0! | S34: =R34/Units -> #DIV/0! | U34: Millage Growth Rate | W34: 0.01 | X34: =W34 -> 0.01 | Y34: =X34 -> 0.01 | Z34: =Y34 -> 0.01 | AA34: =Z34 -> 0.01 | AB34: =AA34 -> 0.01 | AC34: =AB34 -> 0.01 | AD34: =AC34 -> 0.01 | AE34: =AD34 -> 0.01 | AF34: =AE34 -> 0.01
B35: Market Rent Growth | C35: 0.03 | E35: SUBTOTAL | F35: =SUM(F29:F34) -> 0 | G35: =IFERROR(F35/Units,0) -> 0 | I35: =SUM(I29:I34) -> #DIV/0! | J35: =IFERROR(I35/Units,0) -> 0 | L35: =SUM(L29:L34) -> #DIV/0! | M35: =L35/Units -> #DIV/0! | O35: =SUM(O29:O34) -> #DIV/0! | P35: =O35/Units -> #DIV/0! | R35: =SUM(R29:R34) -> #DIV/0! | S35: =R35/Units -> #DIV/0! | U35: Millage Rate | V35: 0.0211718 | W35: =V35*(1+W34) -> 0.021383518 | X35: =W35*(1+X34) -> 0.021597353 | Y35: =X35*(1+Y34) -> 0.021813327 | Z35: =Y35*(1+Z34) -> 0.02203146 | AA35: =Z35*(1+AA34) -> 0.022251775 | AB35: =AA35*(1+AB34) -> 0.022474292 | AC35: =AB35*(1+AC34) -> 0.022699035 | AD35: =AC35*(1+AD34) -> 0.022926026 | ... AF35: =AE35*(1+AF34) -> 0.023386839
B36: MTM Growth | C36: 0.02 | E36: NON-VARIABLE OPERATING EXPENSES | J36: =J35/G35-1 -> #DIV/0! | U36: Property Tax | V36: =V33*V35 -> 1905462 | W36: =W33*W35 -> 1924516.6 | X36: =X33*X35 -> 2159735.3 | Y36: =Y33*Y35 -> 2224959.3 | Z36: =Z33*Z35 -> 2292153.1 | AA36: =AA33*AA35 -> 2361376.1 | AB36: =AB33*AB35 -> 2432689.7 | AC36: =AC33*AC35 -> 2506156.9 | ... AF36: =AF33*AF35 -> 2740140.9
B37: Affordable Growth | C37: 0.03 | E37: Utilities | F37: =IFERROR('T12 Clean'!O35,0) -> 0 | G37: =IFERROR(F37/Units,0) -> 0 | I37: =J37*Units -> 0 | J37: =G37*(1+$C$40) -> 0 | L37: =I37 -> 0 | M37: =L37/Units -> #DIV/0! | O37: =L37 -> 0 | P37: =O37/Units -> #DIV/0! | R37: =O37*(1+$C$40)^($R$3-1) -> 0 | S37: =R37/Units -> #DIV/0! | U37: Non Ad Growth Rate | W37: 0.01 | X37: =W37 -> 0.01 | Y37: =X37 -> 0.01 | Z37: =Y37 -> 0.01 | AA37: =Z37 -> 0.01 | AB37: =AA37 -> 0.01 | AC37: =AB37 -> 0.01 | AD37: =AC37 -> 0.01 | AE37: =AD37 -> 0.01 | AF37: =AE37 -> 0.01
B38: Other Income Growth | C38: 0.03 | E38: Management Fees | F38: =IFERROR('T12 Clean'!O36,0) -> 0 | G38: =IFERROR(F38/'T12 Clean'!O24,0) -> 0 | I38: =J38*I26 -> 0 | J38: 0.02 | L38: =M38*L26 -> #DIV/0! | M38: =J38 -> 0.02 | O38: =P38*O26 -> #DIV/0! | P38: =M38 -> 0.02 | R38: =S38*R26 -> #DIV/0! | S38: =P38 -> 0.02 | U38: Non Ad-Valorem Tax | V38: 50000 | W38: =V38*(1+W37) -> 50500 | X38: =W38*(1+X37) -> 51005 | Y38: =X38*(1+Y37) -> 51515.05 | Z38: =Y38*(1+Z37) -> 52030.201 | AA38: =Z38*(1+AA37) -> 52550.503 | AB38: =AA38*(1+AB37) -> 53076.008 | AC38: =AB38*(1+AC37) -> 53606.768 | AD38: =AC38*(1+AD37) -> 54142.835 | ... AF38: =AE38*(1+AF37) -> 55231.106
B39: Commercial Growth | C39: 0.03 | E39: Insurance | F39: =IFERROR('T12 Clean'!O37,0) -> 0 | G39: =IFERROR(F39/Units,0) -> 0 | I39: =J39*Units -> 0 | J39: =G39*(1+$C$41) -> 0 | L39: =I39 -> 0 | M39: =L39/Units -> #DIV/0! | O39: =L39 -> 0 | P39: =O39/Units -> #DIV/0! | R39: =O39*(1+$C$41)^($R$3-1) -> 0 | S39: =R39/Units -> #DIV/0! | U39: Total RET | V39: =SUM(V36,V38) -> 1955462 | W39: =SUM(W36,W38) -> 1975016.6 | X39: =SUM(X36,X38) -> 2210740.3 | Y39: =SUM(Y36,Y38) -> 2276474.4 | Z39: =SUM(Z36,Z38) -> 2344183.3 | AA39: =SUM(AA36,AA38) -> 2413926.6 | AB39: =SUM(AB36,AB38) -> 2485765.7 | AC39: =SUM(AC36,AC38) -> 2559763.7 | ... AF39: =SUM(AF36,AF38) -> 2795372
B40: Expense Growth | C40: 0.02 | E40: Real Estate Taxes | F40: =IFERROR('T12 Clean'!O38,0) -> 0 | G40: =IFERROR(F40/Units,0) -> 0 | I40: =J40*Units -> #DIV/0! | J40: =Y25/Units -> #DIV/0! | L40: =I40 -> #DIV/0! | M40: =L40/Units -> #DIV/0! | O40: =L40 -> #DIV/0! | P40: =O40/Units -> #DIV/0! | R40: =+HLOOKUP(R3,V43:AE46,4,FALSE) -> 2455832.7 | S40: =R40/Units -> #DIV/0! | U40: Early Payment Discount | V40: 0 | W40: =V40 -> 0 | X40: =W40 -> 0 | Y40: =X40 -> 0 | Z40: =Y40 -> 0 | AA40: =Z40 -> 0 | AB40: =AA40 -> 0 | AC40: =AB40 -> 0 | AD40: =AC40 -> 0 | ... AF40: =AE40 -> 0
B41: Insurance Growth | C41: 0.02 | E41: HOA | F41: =IFERROR('T12 Clean'!O39,0) -> 0 | G41: =IFERROR(F41/Units,0) -> 0 | I41: =J41*Units -> 0 | J41: =G41*(1+$C$40) -> 0 | L41: =I41 -> 0 | M41: =L41/Units -> #DIV/0! | O41: =L41 -> 0 | P41: =O41/Units -> #DIV/0! | R41: =O41*(1+$C$40)^($R$3-1) -> 0 | S41: =R41/Units -> #DIV/0! | U41: Total RET w/ Discount | V41: =V39*(1-V40) -> 1955462 | W41: =W39*(1-W40) -> 1975016.6 | X41: =X39*(1-X40) -> 2210740.3 | Y41: =Y39*(1-Y40) -> 2276474.4 | Z41: =Z39*(1-Z40) -> 2344183.3 | AA41: =AA39*(1-AA40) -> 2413926.6 | AB41: =AB39*(1-AB40) -> 2485765.7 | AC41: =AC39*(1-AC40) -> 2559763.7 | ... AF41: =AF39*(1-AF40) -> 2795372
E42: SUBTOTAL | F42: =SUM(F37:F41) -> 0 | G42: =IFERROR(F42/Units,0) -> 0 | I42: =SUM(I37:I41) -> #DIV/0! | J42: =IFERROR(I42/Units,0) -> 0 | L42: =SUM(L37:L41) -> #DIV/0! | M42: =L42/Units -> #DIV/0! | O42: =SUM(O37:O41) -> #DIV/0! | P42: =O42/Units -> #DIV/0! | R42: =SUM(R37:R41) -> #DIV/0! | S42: =R42/Units -> #DIV/0! | W42: =W41/V41-1 -> 0.01 | X42: =X41/W41-1 -> 0.11935277 | Y42: =Y41/X41-1 -> 0.029733957 | Z42: =Z41/Y41-1 -> 0.029742888 | AA42: =AA41/Z41-1 -> 0.029751652 | AB42: =AB41/AA41-1 -> 0.029760252 | AC42: =AC41/AB41-1 -> 0.02976869 | AD42: =AD41/AC41-1 -> 0.02977697 | ... AF42: =AF41/AE41-1 -> 0.029793066
B43: Stblz Parking Assumptions | C43: =IF(SUM(C44,C49,C54)=C14,C14,"REVIEW") -> 0 | E43: Commercial Expenses | F43: =IFERROR('T12 Clean'!O41,0) -> 0 | G43: =IFERROR(F43/Units,0) -> 0 | I43: =IFERROR('T12 Clean'!O41,0) -> 0 | J43: =G43*(1+$C$40) -> 0 | L43: =I43 -> 0 | M43: =L43/Units -> #DIV/0! | O43: =L43 -> 0 | P43: =O43/Units -> #DIV/0! | R43: =O43*(1+$C$40)^($R$3-1) -> 0 | S43: =R43/Units -> #DIV/0! | U43: Hold Year | V43: 0 | W43: =V43+1 -> 1 | X43: =W43+1 -> 2 | Y43: =X43+1 -> 3 | Z43: =Y43+1 -> 4 | AA43: =Z43+1 -> 5 | AB43: =AA43+1 -> 6 | AC43: =AB43+1 -> 7 | AD43: =AC43+1 -> 8 | AE43: =AD43+1 -> 9
B44: [Description of Space] | C44: =C14 -> 0 | E44: Total Operating Expenses | F44: =SUM(F35,F42:F43) -> 0 | G44: =IFERROR(F44/Units,0) -> 0 | I44: =SUM(I35,I42:I43) -> #DIV/0! | J44: =IFERROR(I44/Units,0) -> 0 | L44: =SUM(L35,L42:L43) -> #DIV/0! | M44: =L44/Units -> #DIV/0! | O44: =SUM(O35,O42:O43) -> #DIV/0! | P44: =O44/Units -> #DIV/0! | R44: =SUM(R35,R42:R43) -> #DIV/0! | S44: =R44/Units -> #DIV/0! | U44: Hold Year Beginning | V44: =EOMONTH(V24,-12) -> 45900 | W44: =EOMONTH(V44,12) -> 46265 | X44: =EOMONTH(W44,12) -> 46630 | Y44: =EOMONTH(X44,12) -> 46996 | Z44: =EOMONTH(Y44,12) -> 47361 | AA44: =EOMONTH(Z44,12) -> 47726 | AB44: =EOMONTH(AA44,12) -> 48091 | AC44: =EOMONTH(AB44,12) -> 48457 | AD44: =EOMONTH(AC44,12) -> 48822 | AE44: =EOMONTH(AD44,12) -> 49187
B45: Monthly Rental Rate | C45: 75 | U45: Hold year Ending | V45: =EOMONTH(V25,-12) -> 46234 | W45: =EOMONTH(V45,12) -> 46599 | X45: =EOMONTH(W45,12) -> 46965 | Y45: =EOMONTH(X45,12) -> 47330 | Z45: =EOMONTH(Y45,12) -> 47695 | AA45: =EOMONTH(Z45,12) -> 48060 | AB45: =EOMONTH(AA45,12) -> 48426 | AC45: =EOMONTH(AB45,12) -> 48791 | AD45: =EOMONTH(AC45,12) -> 49156 | AE45: =EOMONTH(AD45,12) -> 49521
B46: Occupancy % | C46: 0 | E46: Net Operating Income (before Reserves) | F46: =F26-F44 -> 0 | G46: =IFERROR(F46/Units,0) -> 0 | I46: =I26-I44 -> #DIV/0! | J46: =IFERROR(I46/Units,0) -> 0 | L46: =L26-L44 -> #DIV/0! | M46: =L46/Units -> #DIV/0! | O46: =O26-O44 -> #DIV/0! | P46: =O46/Units -> #DIV/0! | R46: =R26-R44 -> #DIV/0! | S46: =R46/Units -> #DIV/0! | U46: RET Expense | V46: =IF(YEAR(V45)=YEAR(V44),V41,(((12-MONTH(V45))*V41)+(MONTH(V45)*W41))/12) -> 1966868.9 | W46: =IF(YEAR(W45)=YEAR(W44),W41,(((12-MONTH(W45))*W41)+(MONTH(W45)*X41))/12) -> 2112522.1 | X46: =IF(YEAR(X45)=YEAR(X44),X41,(((12-MONTH(X45))*X41)+(MONTH(X45)*Y41))/12) -> 2249085.2 | Y46: =IF(YEAR(Y45)=YEAR(Y44),Y41,(((12-MONTH(Y45))*Y41)+(MONTH(Y45)*Z41))/12) -> 2315971.2 | Z46: =IF(YEAR(Z45)=YEAR(Z44),Z41,(((12-MONTH(Z45))*Z41)+(MONTH(Z45)*AA41))/12) -> 2384866.9 | AA46: =IF(YEAR(AA45)=YEAR(AA44),AA41,(((12-MONTH(AA45))*AA41)+(MONTH(AA45)*AB41))/12) -> 2455832.7 | AB46: =IF(YEAR(AB45)=YEAR(AB44),AB41,(((12-MONTH(AB45))*AB41)+(MONTH(AB45)*AC41))/12) -> 2528931.2 | AC46: =IF(YEAR(AC45)=YEAR(AC44),AC41,(((12-MONTH(AC45))*AC41)+(MONTH(AC45)*AD41))/12) -> 2604226.5 | ... AE46: =IF(YEAR(AE45)=YEAR(AE44),AE41,(((12-MONTH(AE45))*AE41)+(MONTH(AE45)*AF41))/12) -> 2761674.8
B47: Total Revenue | C47: =C44*C45*C46*12 -> 0 | E47: Replacement Reserves | F47: =IFERROR('T12 Clean'!O45,0) -> 0 | G47: =IFERROR(F47/Units,0) -> 0 | I47: =J47*Units -> 0 | J47: 300 | L47: =I47 -> 0 | M47: =L47/Units -> #DIV/0! | O47: =P47*Units -> #DIV/0! | P47: =M47+50 -> #DIV/0! | R47: =S47*Units -> #DIV/0! | S47: =P47+50 -> #DIV/0! | W47: =W46/V46-1 -> 0.07405336 | X47: =X46/W46-1 -> 0.064644565 | Y47: =Y46/X46-1 -> 0.02973923 | Z47: =Z46/Y46-1 -> 0.029748063 | AA47: =AA46/Z46-1 -> 0.02975673 | AB47: =AB46/AA46-1 -> 0.029765234 | AC47: =AC46/AB46-1 -> 0.029773579 | AD47: =AD46/AC46-1 -> 0.029781767 | AE47: =AE46/AD46-1 -> 0.029789801
E48: Net Operating Income (after Reserves) | F48: =F46-F47 -> 0 | G48: =IFERROR(F48/Units,0) -> 0 | I48: =I46-I47 -> #DIV/0! | J48: =IFERROR(I48/Units,0) -> 0 | L48: =L46-L47 -> #DIV/0! | M48: =L48/Units -> #DIV/0! | O48: =O46-O47 -> #DIV/0! | P48: =O48/Units -> #DIV/0! | R48: =R46-R47 -> #DIV/0! | S48: =R48/Units -> #DIV/0!
B49: [Description of Space] | C49: 0 | U49: Unit Renovation Summary | V49: Renovation #1 | W49: Renovation #2 | X49: Renovation #3 | Y49: Total/Wtd Avgs
B50: Monthly Rental Rate | C50: 0 | U50: # of Units | V50: =Units -> 0 | W50: 0 | X50: 0 | Y50: =MIN(SUM(V50:X50),Units) -> 0
B51: Occupancy % | C51: 0 | U51: Renovation Premium | V51: 0 | W51: 0 | X51: 0 | Y51: =SUMPRODUCT(V50:X50,V51:X51)/Y50 -> #DIV/0!
B52: Total Revenue | C52: =C49*C50*C51*12 -> 0 | U52: Cost | V52: 0 | W52: 0 | X52: 0 | Y52: =SUMPRODUCT(V50:X50,V52:X52)/Y50 -> #DIV/0!
U53: ROI | V53: =IFERROR(V51*12/V52,0) -> 0 | W53: =IFERROR(W51*12/W52,0) -> 0 | X53: =IFERROR(X51*12/X52,0) -> 0 | Y53: =IFERROR(Y51*12/Y52,0) -> 0
B54: [Description of Space] | C54: 0
B55: Monthly Rental Rate | C55: 0 | U55: Renovation Detail | X55: ROI
B56: Occupancy % | C56: 0 | U56: Unit Renovation $s | W56: =Y50*Y52 -> #DIV/0! | X56: =IFERROR(($Y$51*$Y$50*12)/(W56*(1+$V$59)),0) -> 0
B57: Total Revenue | C57: =C54*C55*C56*12 -> 0 | U57: Common Area / Amenity $s | W57: 1500000 | X57: =IFERROR(($Y$51*$Y$50*12)/(SUM(W56:W57)*(1+$V$59)),0) -> 0
U58: Deferred Maintenance $s | W58: 500000
B59: PARKING GRAND TOTAL | C59: =IF(C47=0,F18*(1+$C$38),SUM(C47,C52,C57)) -> 0 | U59: CM Fee | V59: 0.05 | W59: =V59*SUM(W56,W57) -> #DIV/0!
B60: PARKING T12 (+/- %) | C60: =C59/F18-1 -> #DIV/0! | U60: Total Capital $s | W60: =SUM(W56:W59) -> #DIV/0! | X60: =IFERROR(($Y$51*$Y$50*12)/W60,0) -> 0

Sheet T12 Clean
B1: NPR Trend w/ Conc--> | D1: =(D8+D10)/(C8+C10)-1 -> #DIV/0! | E1: =(E8+E10)/(D8+D10)-1 -> #DIV/0! | F1: =(F8+F10)/(E8+E10)-1 -> #DIV/0! | G1: =(G8+G10)/(F8+F10)-1 -> #DIV/0! | H1: =(H8+H10)/(G8+G10)-1 -> #DIV/0! | I1: =(I8+I10)/(H8+H10)-1 -> #DIV/0! | J1: =(J8+J10)/(I8+I10)-1 -> #DIV/0! | K1: =(K8+K10)/(J8+J10)-1 -> #DIV/0! | ... N1: =(N8+N10)/(M8+M10)-1 -> #DIV/0! | O1: =((N8+N10)/(C8+C10))^(11/12)-1 -> #DIV/0!
B2: Vacancy Trend --> | C2: =C9/C5 -> #DIV/0! | D2: =D9/D5 -> #DIV/0! | E2: =E9/E5 -> #DIV/0! | F2: =F9/F5 -> #DIV/0! | G2: =G9/G5 -> #DIV/0! | H2: =H9/H5 -> #DIV/0! | I2: =I9/I5 -> #DIV/0! | J2: =J9/J5 -> #DIV/0! | ... O2: =O9/O5 -> #DIV/0!
B3: =CONCATENATE('QuickVal Proforma'!C5," | ","T12") -> | T12
B4: RENTAL REVENUE | C4: ='T12 Intake'!D3 -> 45535 | D4: ='T12 Intake'!E3 -> 45565 | E4: ='T12 Intake'!F3 -> 45596 | F4: ='T12 Intake'!G3 -> 45626 | G4: ='T12 Intake'!H3 -> 45657 | H4: ='T12 Intake'!I3 -> 45688 | I4: ='T12 Intake'!J3 -> 45716 | J4: ='T12 Intake'!K3 -> 45747 | ... N4: ='T12 Intake'!O3 -> 45869 | O4: T12 | P4: T6 | Q4: T3 | R4: T1
B5: Gross Potential Rent - Market Rate | C5: =SUMIF('T12 Intake'!$Q$4:$Q$1000,$B5,'T12 Intake'!D$4:D$1000) -> 0 | D5: =SUMIF('T12 Intake'!$Q$4:$Q$1000,$B5,'T12 Intake'!E$4:E$1000) -> 0 | E5: =SUMIF('T12 Intake'!$Q$4:$Q$1000,$B5,'T12 Intake'!F$4:F$1000) -> 0 | F5: =SUMIF('T12 Intake'!$Q$4:$Q$1000,$B5,'T12 Intake'!G$4:G$1000) -> 0 | G5: =SUMIF('T12 Intake'!$Q$4:$Q$1000,$B5,'T12 Intake'!H$4:H$1000) -> 0 | H5: =SUMIF('T12 Intake'!$Q$4:$Q$1000,$B5,'T12 Intake'!I$4:I$1000) -> 0 | I5: =SUMIF('T12 Intake'!$Q$4:$Q$1000,$B5,'T12 Intake'!J$4:J$1000) -> 0 | J5: =SUMIF('T12 Intake'!$Q$4:$Q$1000,$B5,'T12 Intake'!K$4:K$1000) -> 0 | ... O5: =SUMIF('T12 Intake'!$Q$4:$Q$1000,$B5,'T12 Intake'!P$4:P$1000) -> 0 | P5: =SUM(I5:N5)*2 -> 0 | Q5: =SUM(L5:N5)*4 -> 0 | R5: =N5*12 -> 0
B6: Gross Potential Rent - Affordables | C6: =SUMIF('T12 Intake'!$Q$4:$Q$1000,$B6,'T12 Intake'!D$4:D$1000) -> 0 | D6: =SUMIF('T12 Intake'!$Q$4:$Q$1000,$B6,'T12 Intake'!E$4:E$1000) -> 0 | E6: =SUMIF('T12 Intake'!$Q$4:$Q$1000,$B6,'T12 Intake'!F$4:F$1000) -> 0 | F6: =SUMIF('T12 Intake'!$Q$4:$Q$1000,$B6,'T12 Intake'!G$4:G$1000) -> 0 | G6: =SUMIF('T12 Intake'!$Q$4:$Q$1000,$B6,'T12 Intake'!H$4:H$1000) -> 0 | H6: =SUMIF('T12 Intake'!$Q$4:$Q$1000,$B6,'T12 Intake'!I$4:I$1000) -> 0 | I6: =SUMIF('T12 Intake'!$Q$4:$Q$1000,$B6,'T12 Intake'!J$4:J$1000) -> 0 | J6: =SUMIF('T12 Intake'!$Q$4:$Q$1000,$B6,'T12 Intake'!K$4:K$1000) -> 0 | ... O6: =SUMIF('T12 Intake'!$Q$4:$Q$1000,$B6,'T12 Intake'!P$4:P$1000) -> 0 | P6: =SUM(I6:N6)*2 -> 0 | Q6: =SUM(L6:N6)*4 -> 0 | R6: =N6*12 -> 0
B7: Gain / Loss-to-Lease | C7: =SUMIF('T12 Intake'!$Q$4:$Q$1000,$B7,'T12 Intake'!D$4:D$1000) -> 0 | D7: =SUMIF('T12 Intake'!$Q$4:$Q$1000,$B7,'T12 Intake'!E$4:E$1000) -> 0 | E7: =SUMIF('T12 Intake'!$Q$4:$Q$1000,$B7,'T12 Intake'!F$4:F$1000) -> 0 | F7: =SUMIF('T12 Intake'!$Q$4:$Q$1000,$B7,'T12 Intake'!G$4:G$1000) -> 0 | G7: =SUMIF('T12 Intake'!$Q$4:$Q$1000,$B7,'T12 Intake'!H$4:H$1000) -> 0 | H7: =SUMIF('T12 Intake'!$Q$4:$Q$1000,$B7,'T12 Intake'!I$4:I$1000) -> 0 | I7: =SUMIF('T12 Intake'!$Q$4:$Q$1000,$B7,'T12 Intake'!J$4:J$1000) -> 0 | J7: =SUMIF('T12 Intake'!$Q$4:$Q$1000,$B7,'T12 Intake'!K$4:K$1000) -> 0 | ... O7: =SUMIF('T12 Intake'!$Q$4:$Q$1000,$B7,'T12 Intake'!P$4:P$1000) -> 0 | P7: =SUM(I7:N7)*2 -> 0 | Q7: =SUM(L7:N7)*4 -> 0 | R7: =N7*12 -> 0
B8: Net Potential Rent | C8: =SUM(C5:C7) -> 0 | D8: =SUM(D5:D7) -> 0 | E8: =SUM(E5:E7) -> 0 | F8: =SUM(F5:F7) -> 0 | G8: =SUM(G5:G7) -> 0 | H8: =SUM(H5:H7) -> 0 | I8: =SUM(I5:I7) -> 0 | J8: =SUM(J5:J7) -> 0 | ... R8: =SUM(R5:R7) -> 0
B9: Physical Vacancy | C9: =SUMIF('T12 Intake'!$Q$4:$Q$1000,$B9,'T12 Intake'!D$4:D$1000) -> 0 | D9: =SUMIF('T12 Intake'!$Q$4:$Q$1000,$B9,'T12 Intake'!E$4:E$1000) -> 0 | E9: =SUMIF('T12 Intake'!$Q$4:$Q$1000,$B9,'T12 Intake'!F$4:F$1000) -> 0 | F9: =SUMIF('T12 Intake'!$Q$4:$Q$1000,$B9,'T12 Intake'!G$4:G$1000) -> 0 | G9: =SUMIF('T12 Intake'!$Q$4:$Q$1000,$B9,'T12 Intake'!H$4:H$1000) -> 0 | H9: =SUMIF('T12 Intake'!$Q$4:$Q$1000,$B9,'T12 Intake'!I$4:I$1000) -> 0 | I9: =SUMIF('T12 Intake'!$Q$4:$Q$1000,$B9,'T12 Intake'!J$4:J$1000) -> 0 | J9: =SUMIF('T12 Intake'!$Q$4:$Q$1000,$B9,'T12 Intake'!K$4:K$1000) -> 0 | ... O9: =SUMIF('T12 Intake'!$Q$4:$Q$1000,$B9,'T12 Intake'!P$4:P$1000) -> 0 | P9: =SUM(I9:N9)*2 -> 0 | Q9: =SUM(L9:N9)*4 -> 0 | R9: =N9*12 -> 0
B10: Concessions | C10: =SUMIF('T12 Intake'!$Q$4:$Q$1000,$B10,'T12 Intake'!D$4:D$1000) -> 0 | D10: =SUMIF('T12 Intake'!$Q$4:$Q$1000,$B10,'T12 Intake'!E$4:E$1000) -> 0 | E10: =SUMIF('T12 Intake'!$Q$4:$Q$1000,$B10,'T12 Intake'!F$4:F$1000) -> 0 | F10: =SUMIF('T12 Intake'!$Q$4:$Q$1000,$B10,'T12 Intake'!G$4:G$1000) -> 0 | G10: =SUMIF('T12 Intake'!$Q$4:$Q$1000,$B10,'T12 Intake'!H$4:H$1000) -> 0 | H10: =SUMIF('T12 Intake'!$Q$4:$Q$1000,$B10,'T12 Intake'!I$4:I$1000) -> 0 | I10: =SUMIF('T12 Intake'!$Q$4:$Q$1000,$B10,'T12 Intake'!J$4:J$1000) -> 0 | J10: =SUMIF('T12 Intake'!$Q$4:$Q$1000,$B10,'T12 Intake'!K$4:K$1000) -> 0 | ... O10: =SUMIF('T12 Intake'!$Q$4:$Q$1000,$B10,'T12 Intake'!P$4:P$1000) -> 0 | P10: =SUM(I10:N10)*2 -> 0 | Q10: =SUM(L10:N10)*4 -> 0 | R10: =N10*12 -> 0
B11: Employee / Model Units | C11: =SUMIF('T12 Intake'!$Q$4:$Q$1000,$B11,'T12 Intake'!D$4:D$1000) -> 0 | D11: =SUMIF('T12 Intake'!$Q$4:$Q$1000,$B11,'T12 Intake'!E$4:E$1000) -> 0 | E11: =SUMIF('T12 Intake'!$Q$4:$Q$1000,$B11,'T12 Intake'!F$4:F$1000) -> 0 | F11: =SUMIF('T12 Intake'!$Q$4:$Q$1000,$B11,'T12 Intake'!G$4:G$1000) -> 0 | G11: =SUMIF('T12 Intake'!$Q$4:$Q$1000,$B11,'T12 Intake'!H$4:H$1000) -> 0 | H11: =SUMIF('T12 Intake'!$Q$4:$Q$1000,$B11,'T12 Intake'!I$4:I$1000) -> 0 | I11: =SUMIF('T12 Intake'!$Q$4:$Q$1000,$B11,'T12 Intake'!J$4:J$1000) -> 0 | J11: =SUMIF('T12 Intake'!$Q$4:$Q$1000,$B11,'T12 Intake'!K$4:K$1000) -> 0 | ... O11: =SUMIF('T12 Intake'!$Q$4:$Q$1000,$B11,'T12 Intake'!P$4:P$1000) -> 0 | P11: =SUM(I11:N11)*2 -> 0 | Q11: =SUM(L11:N11)*4 -> 0 | R11: =N11*12 -> 0
B12: Down Units | C12: =SUMIF('T12 Intake'!$Q$4:$Q$1000,$B12,'T12 Intake'!D$4:D$1000) -> 0 | D12: =SUMIF('T12 Intake'!$Q$4:$Q$1000,$B12,'T12 Intake'!E$4:E$1000) -> 0 | E12: =SUMIF('T12 Intake'!$Q$4:$Q$1000,$B12,'T12 Intake'!F$4:F$1000) -> 0 | F12: =SUMIF('T12 Intake'!$Q$4:$Q$1000,$B12,'T12 Intake'!G$4:G$1000) -> 0 | G12: =SUMIF('T12 Intake'!$Q$4:$Q$1000,$B12,'T12 Intake'!H$4:H$1000) -> 0 | H12: =SUMIF('T12 Intake'!$Q$4:$Q$1000,$B12,'T12 Intake'!I$4:I$1000) -> 0 | I12: =SUMIF('T12 Intake'!$Q$4:$Q$1000,$B12,'T12 Intake'!J$4:J$1000) -> 0 | J12: =SUMIF('T12 Intake'!$Q$4:$Q$1000,$B12,'T12 Intake'!K$4:K$1000) -> 0 | ... O12: =SUMIF('T12 Intake'!$Q$4:$Q$1000,$B12,'T12 Intake'!P$4:P$1000) -> 0 | P12: =SUM(I12:N12)*2 -> 0 | Q12: =SUM(L12:N12)*4 -> 0 | R12: =N12*12 -> 0
B13: Bad Debt / Write-Offs | C13: =SUMIF('T12 Intake'!$Q$4:$Q$1000,$B13,'T12 Intake'!D$4:D$1000) -> 0 | D13: =SUMIF('T12 Intake'!$Q$4:$Q$1000,$B13,'T12 Intake'!E$4:E$1000) -> 0 | E13: =SUMIF('T12 Intake'!$Q$4:$Q$1000,$B13,'T12 Intake'!F$4:F$1000) -> 0 | F13: =SUMIF('T12 Intake'!$Q$4:$Q$1000,$B13,'T12 Intake'!G$4:G$1000) -> 0 | G13: =SUMIF('T12 Intake'!$Q$4:$Q$1000,$B13,'T12 Intake'!H$4:H$1000) -> 0 | H13: =SUMIF('T12 Intake'!$Q$4:$Q$1000,$B13,'T12 Intake'!I$4:I$1000) -> 0 | I13: =SUMIF('T12 Intake'!$Q$4:$Q$1000,$B13,'T12 Intake'!J$4:J$1000) -> 0 | J13: =SUMIF('T12 Intake'!$Q$4:$Q$1000,$B13,'T12 Intake'!K$4:K$1000) -> 0 | ... O13: =SUMIF('T12 Intake'!$Q$4:$Q$1000,$B13,'T12 Intake'!P$4:P$1000) -> 0 | P13: =SUM(I13:N13)*2 -> 0 | Q13: =SUM(L13:N13)*4 -> 0 | R13: =N13*12 -> 0
B14: Net Rental Income | C14: =SUM(C8:C13) -> 0 | D14: =SUM(D8:D13) -> 0 | E14: =SUM(E8:E13) -> 0 | F14: =SUM(F8:F13) -> 0 | G14: =SUM(G8:G13) -> 0 | H14: =SUM(H8:H13) -> 0 | I14: =SUM(I8:I13) -> 0 | J14: =SUM(J8:J13) -> 0 | ... R14: =SUM(R8:R13) -> 0
B15: OTHER INCOME
B16: Parking | C16: =SUMIF('T12 Intake'!$Q$4:$Q$1000,$B16,'T12 Intake'!D$4:D$1000) -> 0 | D16: =SUMIF('T12 Intake'!$Q$4:$Q$1000,$B16,'T12 Intake'!E$4:E$1000) -> 0 | E16: =SUMIF('T12 Intake'!$Q$4:$Q$1000,$B16,'T12 Intake'!F$4:F$1000) -> 0 | F16: =SUMIF('T12 Intake'!$Q$4:$Q$1000,$B16,'T12 Intake'!G$4:G$1000) -> 0 | G16: =SUMIF('T12 Intake'!$Q$4:$Q$1000,$B16,'T12 Intake'!H$4:H$1000) -> 0 | H16: =SUMIF('T12 Intake'!$Q$4:$Q$1000,$B16,'T12 Intake'!I$4:I$1000) -> 0 | I16: =SUMIF('T12 Intake'!$Q$4:$Q$1000,$B16,'T12 Intake'!J$4:J$1000) -> 0 | J16: =SUMIF('T12 Intake'!$Q$4:$Q$1000,$B16,'T12 Intake'!K$4:K$1000) -> 0 | ... O16: =SUMIF('T12 Intake'!$Q$4:$Q$1000,$B16,'T12 Intake'!P$4:P$1000) -> 0 | P16: =SUM(I16:N16)*2 -> 0 | Q16: =SUM(L16:N16)*4 -> 0 | R16: =N16*12 -> 0
B17: Storage | C17: =SUMIF('T12 Intake'!$Q$4:$Q$1000,$B17,'T12 Intake'!D$4:D$1000) -> 0 | D17: =SUMIF('T12 Intake'!$Q$4:$Q$1000,$B17,'T12 Intake'!E$4:E$1000) -> 0 | E17: =SUMIF('T12 Intake'!$Q$4:$Q$1000,$B17,'T12 Intake'!F$4:F$1000) -> 0 | F17: =SUMIF('T12 Intake'!$Q$4:$Q$1000,$B17,'T12 Intake'!G$4:G$1000) -> 0 | G17: =SUMIF('T12 Intake'!$Q$4:$Q$1000,$B17,'T12 Intake'!H$4:H$1000) -> 0 | H17: =SUMIF('T12 Intake'!$Q$4:$Q$1000,$B17,'T12 Intake'!I$4:I$1000) -> 0 | I17: =SUMIF('T12 Intake'!$Q$4:$Q$1000,$B17,'T12 Intake'!J$4:J$1000) -> 0 | J17: =SUMIF('T12 Intake'!$Q$4:$Q$1000,$B17,'T12 Intake'!K$4:K$1000) -> 0 | ... O17: =SUMIF('T12 Intake'!$Q$4:$Q$1000,$B17,'T12 Intake'!P$4:P$1000) -> 0 | P17: =SUM(I17:N17)*2 -> 0 | Q17: =SUM(L17:N17)*4 -> 0 | R17: =N17*12 -> 0
B18: Pet Fees / Rent | C18: =SUMIF('T12 Intake'!$Q$4:$Q$1000,$B18,'T12 Intake'!D$4:D$1000) -> 0 | D18: =SUMIF('T12 Intake'!$Q$4:$Q$1000,$B18,'T12 Intake'!E$4:E$1000) -> 0 | E18: =SUMIF('T12 Intake'!$Q$4:$Q$1000,$B18,'T12 Intake'!F$4:F$1000) -> 0 | F18: =SUMIF('T12 Intake'!$Q$4:$Q$1000,$B18,'T12 Intake'!G$4:G$1000) -> 0 | G18: =SUMIF('T12 Intake'!$Q$4:$Q$1000,$B18,'T12 Intake'!H$4:H$1000) -> 0 | H18: =SUMIF('T12 Intake'!$Q$4:$Q$1000,$B18,'T12 Intake'!I$4:I$1000) -> 0 | I18: =SUMIF('T12 Intake'!$Q$4:$Q$1000,$B18,'T12 Intake'!J$4:J$1000) -> 0 | J18: =SUMIF('T12 Intake'!$Q$4:$Q$1000,$B18,'T12 Intake'!K$4:K$1000) -> 0 | ... O18: =SUMIF('T12 Intake'!$Q$4:$Q$1000,$B18,'T12 Intake'!P$4:P$1000) -> 0 | P18: =SUM(I18:N18)*2 -> 0 | Q18: =SUM(L18:N18)*4 -> 0 | R18: =N18*12 -> 0
B19: Cable / Internet | C19: =SUMIF('T12 Intake'!$Q$4:$Q$1000,$B19,'T12 Intake'!D$4:D$1000) -> 0 | D19: =SUMIF('T12 Intake'!$Q$4:$Q$1000,$B19,'T12 Intake'!E$4:E$1000) -> 0 | E19: =SUMIF('T12 Intake'!$Q$4:$Q$1000,$B19,'T12 Intake'!F$4:F$1000) -> 0 | F19: =SUMIF('T12 Intake'!$Q$4:$Q$1000,$B19,'T12 Intake'!G$4:G$1000) -> 0 | G19: =SUMIF('T12 Intake'!$Q$4:$Q$1000,$B19,'T12 Intake'!H$4:H$1000) -> 0 | H19: =SUMIF('T12 Intake'!$Q$4:$Q$1000,$B19,'T12 Intake'!I$4:I$1000) -> 0 | I19: =SUMIF('T12 Intake'!$Q$4:$Q$1000,$B19,'T12 Intake'!J$4:J$1000) -> 0 | J19: =SUMIF('T12 Intake'!$Q$4:$Q$1000,$B19,'T12 Intake'!K$4:K$1000) -> 0 | ... O19: =SUMIF('T12 Intake'!$Q$4:$Q$1000,$B19,'T12 Intake'!P$4:P$1000) -> 0 | P19: =SUM(I19:N19)*2 -> 0 | Q19: =SUM(L19:N19)*4 -> 0 | R19: =N19*12 -> 0
B20: Other Income Misc. | C20: =SUMIF('T12 Intake'!$Q$4:$Q$1000,$B20,'T12 Intake'!D$4:D$1000) -> 0 | D20: =SUMIF('T12 Intake'!$Q$4:$Q$1000,$B20,'T12 Intake'!E$4:E$1000) -> 0 | E20: =SUMIF('T12 Intake'!$Q$4:$Q$1000,$B20,'T12 Intake'!F$4:F$1000) -> 0 | F20: =SUMIF('T12 Intake'!$Q$4:$Q$1000,$B20,'T12 Intake'!G$4:G$1000) -> 0 | G20: =SUMIF('T12 Intake'!$Q$4:$Q$1000,$B20,'T12 Intake'!H$4:H$1000) -> 0 | H20: =SUMIF('T12 Intake'!$Q$4:$Q$1000,$B20,'T12 Intake'!I$4:I$1000) -> 0 | I20: =SUMIF('T12 Intake'!$Q$4:$Q$1000,$B20,'T12 Intake'!J$4:J$1000) -> 0 | J20: =SUMIF('T12 Intake'!$Q$4:$Q$1000,$B20,'T12 Intake'!K$4:K$1000) -> 0 | ... O20: =SUMIF('T12 Intake'!$Q$4:$Q$1000,$B20,'T12 Intake'!P$4:P$1000) -> 0 | P20: =SUM(I20:N20)*2 -> 0 | Q20: =SUM(L20:N20)*4 -> 0 | R20: =N20*12 -> 0
B21: Utility Reimbursements | C21: =SUMIF('T12 Intake'!$Q$4:$Q$1000,$B21,'T12 Intake'!D$4:D$1000) -> 0 | D21: =SUMIF('T12 Intake'!$Q$4:$Q$1000,$B21,'T12 Intake'!E$4:E$1000) -> 0 | E21: =SUMIF('T12 Intake'!$Q$4:$Q$1000,$B21,'T12 Intake'!F$4:F$1000) -> 0 | F21: =SUMIF('T12 Intake'!$Q$4:$Q$1000,$B21,'T12 Intake'!G$4:G$1000) -> 0 | G21: =SUMIF('T12 Intake'!$Q$4:$Q$1000,$B21,'T12 Intake'!H$4:H$1000) -> 0 | H21: =SUMIF('T12 Intake'!$Q$4:$Q$1000,$B21,'T12 Intake'!I$4:I$1000) -> 0 | I21: =SUMIF('T12 Intake'!$Q$4:$Q$1000,$B21,'T12 Intake'!J$4:J$1000) -> 0 | J21: =SUMIF('T12 Intake'!$Q$4:$Q$1000,$B21,'T12 Intake'!K$4:K$1000) -> 0 | ... O21: =SUMIF('T12 Intake'!$Q$4:$Q$1000,$B21,'T12 Intake'!P$4:P$1000) -> 0 | P21: =SUM(I21:N21)*2 -> 0 | Q21: =SUM(L21:N21)*4 -> 0 | R21: =N21*12 -> 0
B22: Total Other Income | C22: =SUM(C16:C21) -> 0 | D22: =SUM(D16:D21) -> 0 | E22: =SUM(E16:E21) -> 0 | F22: =SUM(F16:F21) -> 0 | G22: =SUM(G16:G21) -> 0 | H22: =SUM(H16:H21) -> 0 | I22: =SUM(I16:I21) -> 0 | J22: =SUM(J16:J21) -> 0 | ... R22: =SUM(R16:R21) -> 0
B23: Commercial Income | C23: =SUMIF('T12 Intake'!$Q$4:$Q$1000,$B23,'T12 Intake'!D$4:D$1000) -> 0 | D23: =SUMIF('T12 Intake'!$Q$4:$Q$1000,$B23,'T12 Intake'!E$4:E$1000) -> 0 | E23: =SUMIF('T12 Intake'!$Q$4:$Q$1000,$B23,'T12 Intake'!F$4:F$1000) -> 0 | F23: =SUMIF('T12 Intake'!$Q$4:$Q$1000,$B23,'T12 Intake'!G$4:G$1000) -> 0 | G23: =SUMIF('T12 Intake'!$Q$4:$Q$1000,$B23,'T12 Intake'!H$4:H$1000) -> 0 | H23: =SUMIF('T12 Intake'!$Q$4:$Q$1000,$B23,'T12 Intake'!I$4:I$1000) -> 0 | I23: =SUMIF('T12 Intake'!$Q$4:$Q$1000,$B23,'T12 Intake'!J$4:J$1000) -> 0 | J23: =SUMIF('T12 Intake'!$Q$4:$Q$1000,$B23,'T12 Intake'!K$4:K$1000) -> 0 | ... O23: =SUMIF('T12 Intake'!$Q$4:$Q$1000,$B23,'T12 Intake'!P$4:P$1000) -> 0 | P23: =SUM(I23:N23)*2 -> 0 | Q23: =SUM(L23:N23)*4 -> 0 | R23: =N23*12 -> 0
B24: Effective Gross Income | C24: =SUM(C14,C22:C23) -> 0 | D24: =SUM(D14,D22:D23) -> 0 | E24: =SUM(E14,E22:E23) -> 0 | F24: =SUM(F14,F22:F23) -> 0 | G24: =SUM(G14,G22:G23) -> 0 | H24: =SUM(H14,H22:H23) -> 0 | I24: =SUM(I14,I22:I23) -> 0 | J24: =SUM(J14,J22:J23) -> 0 | ... R24: =SUM(R14,R22:R23) -> 0
B26: VARIABLE OPERATING EXPENSES | C26: =C4 -> 45535 | D26: =D4 -> 45565 | E26: =E4 -> 45596 | F26: =F4 -> 45626 | G26: =G4 -> 45657 | H26: =H4 -> 45688 | I26: =I4 -> 45716 | J26: =J4 -> 45747 | ... R26: =R4 -> T1
B27: Advertising / Marketing | C27: =SUMIF('T12 Intake'!$Q$4:$Q$1000,$B27,'T12 Intake'!D$4:D$1000) -> 0 | D27: =SUMIF('T12 Intake'!$Q$4:$Q$1000,$B27,'T12 Intake'!E$4:E$1000) -> 0 | E27: =SUMIF('T12 Intake'!$Q$4:$Q$1000,$B27,'T12 Intake'!F$4:F$1000) -> 0 | F27: =SUMIF('T12 Intake'!$Q$4:$Q$1000,$B27,'T12 Intake'!G$4:G$1000) -> 0 | G27: =SUMIF('T12 Intake'!$Q$4:$Q$1000,$B27,'T12 Intake'!H$4:H$1000) -> 0 | H27: =SUMIF('T12 Intake'!$Q$4:$Q$1000,$B27,'T12 Intake'!I$4:I$1000) -> 0 | I27: =SUMIF('T12 Intake'!$Q$4:$Q$1000,$B27,'T12 Intake'!J$4:J$1000) -> 0 | J27: =SUMIF('T12 Intake'!$Q$4:$Q$1000,$B27,'T12 Intake'!K$4:K$1000) -> 0 | ... O27: =SUMIF('T12 Intake'!$Q$4:$Q$1000,$B27,'T12 Intake'!P$4:P$1000) -> 0 | P27: =SUM(I27:N27)*2 -> 0 | Q27: =SUM(L27:N27)*4 -> 0 | R27: =N27*12 -> 0
B28: Administrative | C28: =SUMIF('T12 Intake'!$Q$4:$Q$1000,$B28,'T12 Intake'!D$4:D$1000) -> 0 | D28: =SUMIF('T12 Intake'!$Q$4:$Q$1000,$B28,'T12 Intake'!E$4:E$1000) -> 0 | E28: =SUMIF('T12 Intake'!$Q$4:$Q$1000,$B28,'T12 Intake'!F$4:F$1000) -> 0 | F28: =SUMIF('T12 Intake'!$Q$4:$Q$1000,$B28,'T12 Intake'!G$4:G$1000) -> 0 | G28: =SUMIF('T12 Intake'!$Q$4:$Q$1000,$B28,'T12 Intake'!H$4:H$1000) -> 0 | H28: =SUMIF('T12 Intake'!$Q$4:$Q$1000,$B28,'T12 Intake'!I$4:I$1000) -> 0 | I28: =SUMIF('T12 Intake'!$Q$4:$Q$1000,$B28,'T12 Intake'!J$4:J$1000) -> 0 | J28: =SUMIF('T12 Intake'!$Q$4:$Q$1000,$B28,'T12 Intake'!K$4:K$1000) -> 0 | ... O28: =SUMIF('T12 Intake'!$Q$4:$Q$1000,$B28,'T12 Intake'!P$4:P$1000) -> 0 | P28: =SUM(I28:N28)*2 -> 0 | Q28: =SUM(L28:N28)*4 -> 0 | R28: =N28*12 -> 0
B29: Repairs & Maintenance | C29: =SUMIF('T12 Intake'!$Q$4:$Q$1000,$B29,'T12 Intake'!D$4:D$1000) -> 0 | D29: =SUMIF('T12 Intake'!$Q$4:$Q$1000,$B29,'T12 Intake'!E$4:E$1000) -> 0 | E29: =SUMIF('T12 Intake'!$Q$4:$Q$1000,$B29,'T12 Intake'!F$4:F$1000) -> 0 | F29: =SUMIF('T12 Intake'!$Q$4:$Q$1000,$B29,'T12 Intake'!G$4:G$1000) -> 0 | G29: =SUMIF('T12 Intake'!$Q$4:$Q$1000,$B29,'T12 Intake'!H$4:H$1000) -> 0 | H29: =SUMIF('T12 Intake'!$Q$4:$Q$1000,$B29,'T12 Intake'!I$4:I$1000) -> 0 | I29: =SUMIF('T12 Intake'!$Q$4:$Q$1000,$B29,'T12 Intake'!J$4:J$1000) -> 0 | J29: =SUMIF('T12 Intake'!$Q$4:$Q$1000,$B29,'T12 Intake'!K$4:K$1000) -> 0 | ... O29: =SUMIF('T12 Intake'!$Q$4:$Q$1000,$B29,'T12 Intake'!P$4:P$1000) -> 0 | P29: =SUM(I29:N29)*2 -> 0 | Q29: =SUM(L29:N29)*4 -> 0 | R29: =N29*12 -> 0
B30: Contract Services | C30: =SUMIF('T12 Intake'!$Q$4:$Q$1000,$B30,'T12 Intake'!D$4:D$1000) -> 0 | D30: =SUMIF('T12 Intake'!$Q$4:$Q$1000,$B30,'T12 Intake'!E$4:E$1000) -> 0 | E30: =SUMIF('T12 Intake'!$Q$4:$Q$1000,$B30,'T12 Intake'!F$4:F$1000) -> 0 | F30: =SUMIF('T12 Intake'!$Q$4:$Q$1000,$B30,'T12 Intake'!G$4:G$1000) -> 0 | G30: =SUMIF('T12 Intake'!$Q$4:$Q$1000,$B30,'T12 Intake'!H$4:H$1000) -> 0 | H30: =SUMIF('T12 Intake'!$Q$4:$Q$1000,$B30,'T12 Intake'!I$4:I$1000) -> 0 | I30: =SUMIF('T12 Intake'!$Q$4:$Q$1000,$B30,'T12 Intake'!J$4:J$1000) -> 0 | J30: =SUMIF('T12 Intake'!$Q$4:$Q$1000,$B30,'T12 Intake'!K$4:K$1000) -> 0 | ... O30: =SUMIF('T12 Intake'!$Q$4:$Q$1000,$B30,'T12 Intake'!P$4:P$1000) -> 0 | P30: =SUM(I30:N30)*2 -> 0 | Q30: =SUM(L30:N30)*4 -> 0 | R30: =N30*12 -> 0
B31: Turnover / Make Ready | C31: =SUMIF('T12 Intake'!$Q$4:$Q$1000,$B31,'T12 Intake'!D$4:D$1000) -> 0 | D31: =SUMIF('T12 Intake'!$Q$4:$Q$1000,$B31,'T12 Intake'!E$4:E$1000) -> 0 | E31: =SUMIF('T12 Intake'!$Q$4:$Q$1000,$B31,'T12 Intake'!F$4:F$1000) -> 0 | F31: =SUMIF('T12 Intake'!$Q$4:$Q$1000,$B31,'T12 Intake'!G$4:G$1000) -> 0 | G31: =SUMIF('T12 Intake'!$Q$4:$Q$1000,$B31,'T12 Intake'!H$4:H$1000) -> 0 | H31: =SUMIF('T12 Intake'!$Q$4:$Q$1000,$B31,'T12 Intake'!I$4:I$1000) -> 0 | I31: =SUMIF('T12 Intake'!$Q$4:$Q$1000,$B31,'T12 Intake'!J$4:J$1000) -> 0 | J31: =SUMIF('T12 Intake'!$Q$4:$Q$1000,$B31,'T12 Intake'!K$4:K$1000) -> 0 | ... O31: =SUMIF('T12 Intake'!$Q$4:$Q$1000,$B31,'T12 Intake'!P$4:P$1000) -> 0 | P31: =SUM(I31:N31)*2 -> 0 | Q31: =SUM(L31:N31)*4 -> 0 | R31: =N31*12 -> 0
B32: Payroll & Benefits | C32: =SUMIF('T12 Intake'!$Q$4:$Q$1000,$B32,'T12 Intake'!D$4:D$1000) -> 0 | D32: =SUMIF('T12 Intake'!$Q$4:$Q$1000,$B32,'T12 Intake'!E$4:E$1000) -> 0 | E32: =SUMIF('T12 Intake'!$Q$4:$Q$1000,$B32,'T12 Intake'!F$4:F$1000) -> 0 | F32: =SUMIF('T12 Intake'!$Q$4:$Q$1000,$B32,'T12 Intake'!G$4:G$1000) -> 0 | G32: =SUMIF('T12 Intake'!$Q$4:$Q$1000,$B32,'T12 Intake'!H$4:H$1000) -> 0 | H32: =SUMIF('T12 Intake'!$Q$4:$Q$1000,$B32,'T12 Intake'!I$4:I$1000) -> 0 | I32: =SUMIF('T12 Intake'!$Q$4:$Q$1000,$B32,'T12 Intake'!J$4:J$1000) -> 0 | J32: =SUMIF('T12 Intake'!$Q$4:$Q$1000,$B32,'T12 Intake'!K$4:K$1000) -> 0 | ... O32: =SUMIF('T12 Intake'!$Q$4:$Q$1000,$B32,'T12 Intake'!P$4:P$1000) -> 0 | P32: =SUM(I32:N32)*2 -> 0 | Q32: =SUM(L32:N32)*4 -> 0 | R32: =N32*12 -> 0
B33: SUBTOTAL | C33: =SUM(C27:C32) -> 0 | D33: =SUM(D27:D32) -> 0 | E33: =SUM(E27:E32) -> 0 | F33: =SUM(F27:F32) -> 0 | G33: =SUM(G27:G32) -> 0 | H33: =SUM(H27:H32) -> 0 | I33: =SUM(I27:I32) -> 0 | J33: =SUM(J27:J32) -> 0 | ... R33: =SUM(R27:R32) -> 0
B34: NON-VARIABLE OPERATING EXPENSES
B35: Utilities | C35: =SUMIF('T12 Intake'!$Q$4:$Q$1000,$B35,'T12 Intake'!D$4:D$1000) -> 0 | D35: =SUMIF('T12 Intake'!$Q$4:$Q$1000,$B35,'T12 Intake'!E$4:E$1000) -> 0 | E35: =SUMIF('T12 Intake'!$Q$4:$Q$1000,$B35,'T12 Intake'!F$4:F$1000) -> 0 | F35: =SUMIF('T12 Intake'!$Q$4:$Q$1000,$B35,'T12 Intake'!G$4:G$1000) -> 0 | G35: =SUMIF('T12 Intake'!$Q$4:$Q$1000,$B35,'T12 Intake'!H$4:H$1000) -> 0 | H35: =SUMIF('T12 Intake'!$Q$4:$Q$1000,$B35,'T12 Intake'!I$4:I$1000) -> 0 | I35: =SUMIF('T12 Intake'!$Q$4:$Q$1000,$B35,'T12 Intake'!J$4:J$1000) -> 0 | J35: =SUMIF('T12 Intake'!$Q$4:$Q$1000,$B35,'T12 Intake'!K$4:K$1000) -> 0 | ... O35: =SUMIF('T12 Intake'!$Q$4:$Q$1000,$B35,'T12 Intake'!P$4:P$1000) -> 0 | P35: =SUM(I35:N35)*2 -> 0 | Q35: =SUM(L35:N35)*4 -> 0 | R35: =N35*12 -> 0
B36: =CONCATENATE("Mgmt Fees (",ROUND(O36/O24*100,2),"% or $",ROUND(O36/12/Units,0),"/unit/mo.)") -> #DIV/0! | C36: =SUMIF('T12 Intake'!$Q$4:$Q$1000,'T12 Intake'!$S$26,'T12 Intake'!D$4:D$1000) -> 0 | D36: =SUMIF('T12 Intake'!$Q$4:$Q$1000,'T12 Intake'!$S$26,'T12 Intake'!E$4:E$1000) -> 0 | E36: =SUMIF('T12 Intake'!$Q$4:$Q$1000,'T12 Intake'!$S$26,'T12 Intake'!F$4:F$1000) -> 0 | F36: =SUMIF('T12 Intake'!$Q$4:$Q$1000,'T12 Intake'!$S$26,'T12 Intake'!G$4:G$1000) -> 0 | G36: =SUMIF('T12 Intake'!$Q$4:$Q$1000,'T12 Intake'!$S$26,'T12 Intake'!H$4:H$1000) -> 0 | H36: =SUMIF('T12 Intake'!$Q$4:$Q$1000,'T12 Intake'!$S$26,'T12 Intake'!I$4:I$1000) -> 0 | I36: =SUMIF('T12 Intake'!$Q$4:$Q$1000,'T12 Intake'!$S$26,'T12 Intake'!J$4:J$1000) -> 0 | J36: =SUMIF('T12 Intake'!$Q$4:$Q$1000,'T12 Intake'!$S$26,'T12 Intake'!K$4:K$1000) -> 0 | ... O36: =SUMIF('T12 Intake'!$Q$4:$Q$1000,'T12 Intake'!$S$26,'T12 Intake'!P$4:P$1000) -> 0 | P36: =SUM(I36:N36)*2 -> 0 | Q36: =SUM(L36:N36)*4 -> 0 | R36: =N36*12 -> 0
B37: =CONCATENATE('T12 Intake'!$S$27," ($",ROUND(O37/Units,0),"/unit)") -> #DIV/0! | C37: =SUMIF('T12 Intake'!$Q$4:$Q$1000,'T12 Intake'!$S$27,'T12 Intake'!D$4:D$1000) -> 0 | D37: =SUMIF('T12 Intake'!$Q$4:$Q$1000,'T12 Intake'!$S$27,'T12 Intake'!E$4:E$1000) -> 0 | E37: =SUMIF('T12 Intake'!$Q$4:$Q$1000,'T12 Intake'!$S$27,'T12 Intake'!F$4:F$1000) -> 0 | F37: =SUMIF('T12 Intake'!$Q$4:$Q$1000,'T12 Intake'!$S$27,'T12 Intake'!G$4:G$1000) -> 0 | G37: =SUMIF('T12 Intake'!$Q$4:$Q$1000,'T12 Intake'!$S$27,'T12 Intake'!H$4:H$1000) -> 0 | H37: =SUMIF('T12 Intake'!$Q$4:$Q$1000,'T12 Intake'!$S$27,'T12 Intake'!I$4:I$1000) -> 0 | I37: =SUMIF('T12 Intake'!$Q$4:$Q$1000,'T12 Intake'!$S$27,'T12 Intake'!J$4:J$1000) -> 0 | J37: =SUMIF('T12 Intake'!$Q$4:$Q$1000,'T12 Intake'!$S$27,'T12 Intake'!K$4:K$1000) -> 0 | ... O37: =SUMIF('T12 Intake'!$Q$4:$Q$1000,'T12 Intake'!$S$27,'T12 Intake'!P$4:P$1000) -> 0 | P37: =SUM(I37:N37)*2 -> 0 | Q37: =SUM(L37:N37)*4 -> 0 | R37: =N37*12 -> 0
B38: Real Estate Taxes | C38: =SUMIF('T12 Intake'!$Q$4:$Q$1000,$B38,'T12 Intake'!D$4:D$1000) -> 0 | D38: =SUMIF('T12 Intake'!$Q$4:$Q$1000,$B38,'T12 Intake'!E$4:E$1000) -> 0 | E38: =SUMIF('T12 Intake'!$Q$4:$Q$1000,$B38,'T12 Intake'!F$4:F$1000) -> 0 | F38: =SUMIF('T12 Intake'!$Q$4:$Q$1000,$B38,'T12 Intake'!G$4:G$1000) -> 0 | G38: =SUMIF('T12 Intake'!$Q$4:$Q$1000,$B38,'T12 Intake'!H$4:H$1000) -> 0 | H38: =SUMIF('T12 Intake'!$Q$4:$Q$1000,$B38,'T12 Intake'!I$4:I$1000) -> 0 | I38: =SUMIF('T12 Intake'!$Q$4:$Q$1000,$B38,'T12 Intake'!J$4:J$1000) -> 0 | J38: =SUMIF('T12 Intake'!$Q$4:$Q$1000,$B38,'T12 Intake'!K$4:K$1000) -> 0 | ... O38: =SUMIF('T12 Intake'!$Q$4:$Q$1000,$B38,'T12 Intake'!P$4:P$1000) -> 0 | P38: =SUM(I38:N38)*2 -> 0 | Q38: =SUM(L38:N38)*4 -> 0 | R38: =N38*12 -> 0
B39: HOA | C39: =SUMIF('T12 Intake'!$Q$4:$Q$1000,$B39,'T12 Intake'!D$4:D$1000) -> 0 | D39: =SUMIF('T12 Intake'!$Q$4:$Q$1000,$B39,'T12 Intake'!E$4:E$1000) -> 0 | E39: =SUMIF('T12 Intake'!$Q$4:$Q$1000,$B39,'T12 Intake'!F$4:F$1000) -> 0 | F39: =SUMIF('T12 Intake'!$Q$4:$Q$1000,$B39,'T12 Intake'!G$4:G$1000) -> 0 | G39: =SUMIF('T12 Intake'!$Q$4:$Q$1000,$B39,'T12 Intake'!H$4:H$1000) -> 0 | H39: =SUMIF('T12 Intake'!$Q$4:$Q$1000,$B39,'T12 Intake'!I$4:I$1000) -> 0 | I39: =SUMIF('T12 Intake'!$Q$4:$Q$1000,$B39,'T12 Intake'!J$4:J$1000) -> 0 | J39: =SUMIF('T12 Intake'!$Q$4:$Q$1000,$B39,'T12 Intake'!K$4:K$1000) -> 0 | ... O39: =SUMIF('T12 Intake'!$Q$4:$Q$1000,$B39,'T12 Intake'!P$4:P$1000) -> 0 | P39: =SUM(I39:N39)*2 -> 0 | Q39: =SUM(L39:N39)*4 -> 0 | R39: =N39*12 -> 0
B40: SUBTOTAL | C40: =SUM(C35:C39) -> 0 | D40: =SUM(D35:D39) -> 0 | E40: =SUM(E35:E39) -> 0 | F40: =SUM(F35:F39) -> 0 | G40: =SUM(G35:G39) -> 0 | H40: =SUM(H35:H39) -> 0 | I40: =SUM(I35:I39) -> 0 | J40: =SUM(J35:J39) -> 0 | ... R40: =SUM(R35:R39) -> 0
B41: Commercial Expenses | C41: =SUMIF('T12 Intake'!$Q$4:$Q$1000,$B41,'T12 Intake'!D$4:D$1000) -> 0 | D41: =SUMIF('T12 Intake'!$Q$4:$Q$1000,$B41,'T12 Intake'!E$4:E$1000) -> 0 | E41: =SUMIF('T12 Intake'!$Q$4:$Q$1000,$B41,'T12 Intake'!F$4:F$1000) -> 0 | F41: =SUMIF('T12 Intake'!$Q$4:$Q$1000,$B41,'T12 Intake'!G$4:G$1000) -> 0 | G41: =SUMIF('T12 Intake'!$Q$4:$Q$1000,$B41,'T12 Intake'!H$4:H$1000) -> 0 | H41: =SUMIF('T12 Intake'!$Q$4:$Q$1000,$B41,'T12 Intake'!I$4:I$1000) -> 0 | I41: =SUMIF('T12 Intake'!$Q$4:$Q$1000,$B41,'T12 Intake'!J$4:J$1000) -> 0 | J41: =SUMIF('T12 Intake'!$Q$4:$Q$1000,$B41,'T12 Intake'!K$4:K$1000) -> 0 | ... O41: =SUMIF('T12 Intake'!$Q$4:$Q$1000,$B41,'T12 Intake'!P$4:P$1000) -> 0 | P41: =SUM(I41:N41)*2 -> 0 | Q41: =SUM(L41:N41)*4 -> 0 | R41: =N41*12 -> 0
B42: Total Operating Expenses | C42: =SUM(C33,C40:C41) -> 0 | D42: =SUM(D33,D40:D41) -> 0 | E42: =SUM(E33,E40:E41) -> 0 | F42: =SUM(F33,F40:F41) -> 0 | G42: =SUM(G33,G40:G41) -> 0 | H42: =SUM(H33,H40:H41) -> 0 | I42: =SUM(I33,I40:I41) -> 0 | J42: =SUM(J33,J40:J41) -> 0 | ... R42: =SUM(R33,R40:R41) -> 0
B44: Net Operating Income (before Repl. Reserves) | C44: =C24-C42 -> 0 | D44: =D24-D42 -> 0 | E44: =E24-E42 -> 0 | F44: =F24-F42 -> 0 | G44: =G24-G42 -> 0 | H44: =H24-H42 -> 0 | I44: =I24-I42 -> 0 | J44: =J24-J42 -> 0 | ... R44: =R24-R42 -> 0
B45: Replacement Reserves | C45: =SUMIF('T12 Intake'!$Q$4:$Q$1000,$B45,'T12 Intake'!D$4:D$1000) -> 0 | D45: =SUMIF('T12 Intake'!$Q$4:$Q$1000,$B45,'T12 Intake'!E$4:E$1000) -> 0 | E45: =SUMIF('T12 Intake'!$Q$4:$Q$1000,$B45,'T12 Intake'!F$4:F$1000) -> 0 | F45: =SUMIF('T12 Intake'!$Q$4:$Q$1000,$B45,'T12 Intake'!G$4:G$1000) -> 0 | G45: =SUMIF('T12 Intake'!$Q$4:$Q$1000,$B45,'T12 Intake'!H$4:H$1000) -> 0 | H45: =SUMIF('T12 Intake'!$Q$4:$Q$1000,$B45,'T12 Intake'!I$4:I$1000) -> 0 | I45: =SUMIF('T12 Intake'!$Q$4:$Q$1000,$B45,'T12 Intake'!J$4:J$1000) -> 0 | J45: =SUMIF('T12 Intake'!$Q$4:$Q$1000,$B45,'T12 Intake'!K$4:K$1000) -> 0 | ... O45: =SUMIF('T12 Intake'!$Q$4:$Q$1000,$B45,'T12 Intake'!P$4:P$1000) -> 0 | P45: =SUM(I45:N45)*2 -> 0 | Q45: =SUM(L45:N45)*4 -> 0 | R45: =N45*12 -> 0
B46: Net Operating Income (after Repl. Reserves) | C46: =C44-C45 -> 0 | D46: =D44-D45 -> 0 | E46: =E44-E45 -> 0 | F46: =F44-F45 -> 0 | G46: =G44-G45 -> 0 | H46: =H44-H45 -> 0 | I46: =I44-I45 -> 0 | J46: =J44-J45 -> 0 | ... R46: =R44-R45 -> 0
B48: CAPITAL EXPENSES
B49: Non-Recurring CapEx | C49: =SUMIF('T12 Intake'!$Q$4:$Q$1000,$B49,'T12 Intake'!D$4:D$1000) -> 0 | D49: =SUMIF('T12 Intake'!$Q$4:$Q$1000,$B49,'T12 Intake'!E$4:E$1000) -> 0 | E49: =SUMIF('T12 Intake'!$Q$4:$Q$1000,$B49,'T12 Intake'!F$4:F$1000) -> 0 | F49: =SUMIF('T12 Intake'!$Q$4:$Q$1000,$B49,'T12 Intake'!G$4:G$1000) -> 0 | G49: =SUMIF('T12 Intake'!$Q$4:$Q$1000,$B49,'T12 Intake'!H$4:H$1000) -> 0 | H49: =SUMIF('T12 Intake'!$Q$4:$Q$1000,$B49,'T12 Intake'!I$4:I$1000) -> 0 | I49: =SUMIF('T12 Intake'!$Q$4:$Q$1000,$B49,'T12 Intake'!J$4:J$1000) -> 0 | J49: =SUMIF('T12 Intake'!$Q$4:$Q$1000,$B49,'T12 Intake'!K$4:K$1000) -> 0 | ... O49: =SUMIF('T12 Intake'!$Q$4:$Q$1000,$B49,'T12 Intake'!P$4:P$1000) -> 0
B50: Amenity / Common Area CapEx | C50: =SUMIF('T12 Intake'!$Q$4:$Q$1000,$B50,'T12 Intake'!D$4:D$1000) -> 0 | D50: =SUMIF('T12 Intake'!$Q$4:$Q$1000,$B50,'T12 Intake'!E$4:E$1000) -> 0 | E50: =SUMIF('T12 Intake'!$Q$4:$Q$1000,$B50,'T12 Intake'!F$4:F$1000) -> 0 | F50: =SUMIF('T12 Intake'!$Q$4:$Q$1000,$B50,'T12 Intake'!G$4:G$1000) -> 0 | G50: =SUMIF('T12 Intake'!$Q$4:$Q$1000,$B50,'T12 Intake'!H$4:H$1000) -> 0 | H50: =SUMIF('T12 Intake'!$Q$4:$Q$1000,$B50,'T12 Intake'!I$4:I$1000) -> 0 | I50: =SUMIF('T12 Intake'!$Q$4:$Q$1000,$B50,'T12 Intake'!J$4:J$1000) -> 0 | J50: =SUMIF('T12 Intake'!$Q$4:$Q$1000,$B50,'T12 Intake'!K$4:K$1000) -> 0 | ... O50: =SUMIF('T12 Intake'!$Q$4:$Q$1000,$B50,'T12 Intake'!P$4:P$1000) -> 0
B51: Unit Interior CapEx | C51: =SUMIF('T12 Intake'!$Q$4:$Q$1000,$B51,'T12 Intake'!D$4:D$1000) -> 0 | D51: =SUMIF('T12 Intake'!$Q$4:$Q$1000,$B51,'T12 Intake'!E$4:E$1000) -> 0 | E51: =SUMIF('T12 Intake'!$Q$4:$Q$1000,$B51,'T12 Intake'!F$4:F$1000) -> 0 | F51: =SUMIF('T12 Intake'!$Q$4:$Q$1000,$B51,'T12 Intake'!G$4:G$1000) -> 0 | G51: =SUMIF('T12 Intake'!$Q$4:$Q$1000,$B51,'T12 Intake'!H$4:H$1000) -> 0 | H51: =SUMIF('T12 Intake'!$Q$4:$Q$1000,$B51,'T12 Intake'!I$4:I$1000) -> 0 | I51: =SUMIF('T12 Intake'!$Q$4:$Q$1000,$B51,'T12 Intake'!J$4:J$1000) -> 0 | J51: =SUMIF('T12 Intake'!$Q$4:$Q$1000,$B51,'T12 Intake'!K$4:K$1000) -> 0 | ... O51: =SUMIF('T12 Intake'!$Q$4:$Q$1000,$B51,'T12 Intake'!P$4:P$1000) -> 0
B52: TI&LC Expenditures | C52: =SUMIF('T12 Intake'!$Q$4:$Q$1000,$B52,'T12 Intake'!D$4:D$1000) -> 0 | D52: =SUMIF('T12 Intake'!$Q$4:$Q$1000,$B52,'T12 Intake'!E$4:E$1000) -> 0 | E52: =SUMIF('T12 Intake'!$Q$4:$Q$1000,$B52,'T12 Intake'!F$4:F$1000) -> 0 | F52: =SUMIF('T12 Intake'!$Q$4:$Q$1000,$B52,'T12 Intake'!G$4:G$1000) -> 0 | G52: =SUMIF('T12 Intake'!$Q$4:$Q$1000,$B52,'T12 Intake'!H$4:H$1000) -> 0 | H52: =SUMIF('T12 Intake'!$Q$4:$Q$1000,$B52,'T12 Intake'!I$4:I$1000) -> 0 | I52: =SUMIF('T12 Intake'!$Q$4:$Q$1000,$B52,'T12 Intake'!J$4:J$1000) -> 0 | J52: =SUMIF('T12 Intake'!$Q$4:$Q$1000,$B52,'T12 Intake'!K$4:K$1000) -> 0 | ... O52: =SUMIF('T12 Intake'!$Q$4:$Q$1000,$B52,'T12 Intake'!P$4:P$1000) -> 0
B53: Total Capital Expenses | C53: =SUM(C49:C52) -> 0 | D53: =SUM(D49:D52) -> 0 | E53: =SUM(E49:E52) -> 0 | F53: =SUM(F49:F52) -> 0 | G53: =SUM(G49:G52) -> 0 | H53: =SUM(H49:H52) -> 0 | I53: =SUM(I49:I52) -> 0 | J53: =SUM(J49:J52) -> 0 | ... O53: =SUM(O49:O52) -> 0
B55: Operating Cash Flow | C55: =C46-C53 -> 0 | D55: =D46-D53 -> 0 | E55: =E46-E53 -> 0 | F55: =F46-F53 -> 0 | G55: =G46-G53 -> 0 | H55: =H46-H53 -> 0 | I55: =I46-I53 -> 0 | J55: =J46-J53 -> 0 | ... O55: =O46-O53 -> 0
B56: N/A Income / Entity Income | C56: =SUMIF('T12 Intake'!$Q$4:$Q$1000,$B56,'T12 Intake'!D$4:D$1000) -> 0 | D56: =SUMIF('T12 Intake'!$Q$4:$Q$1000,$B56,'T12 Intake'!E$4:E$1000) -> 0 | E56: =SUMIF('T12 Intake'!$Q$4:$Q$1000,$B56,'T12 Intake'!F$4:F$1000) -> 0 | F56: =SUMIF('T12 Intake'!$Q$4:$Q$1000,$B56,'T12 Intake'!G$4:G$1000) -> 0 | G56: =SUMIF('T12 Intake'!$Q$4:$Q$1000,$B56,'T12 Intake'!H$4:H$1000) -> 0 | H56: =SUMIF('T12 Intake'!$Q$4:$Q$1000,$B56,'T12 Intake'!I$4:I$1000) -> 0 | I56: =SUMIF('T12 Intake'!$Q$4:$Q$1000,$B56,'T12 Intake'!J$4:J$1000) -> 0 | J56: =SUMIF('T12 Intake'!$Q$4:$Q$1000,$B56,'T12 Intake'!K$4:K$1000) -> 0 | ... O56: =SUMIF('T12 Intake'!$Q$4:$Q$1000,$B56,'T12 Intake'!P$4:P$1000) -> 0
B57: N/A Expenses / Entity Expenses | C57: =SUMIF('T12 Intake'!$Q$4:$Q$1000,$B57,'T12 Intake'!D$4:D$1000) -> 0 | D57: =SUMIF('T12 Intake'!$Q$4:$Q$1000,$B57,'T12 Intake'!E$4:E$1000) -> 0 | E57: =SUMIF('T12 Intake'!$Q$4:$Q$1000,$B57,'T12 Intake'!F$4:F$1000) -> 0 | F57: =SUMIF('T12 Intake'!$Q$4:$Q$1000,$B57,'T12 Intake'!G$4:G$1000) -> 0 | G57: =SUMIF('T12 Intake'!$Q$4:$Q$1000,$B57,'T12 Intake'!H$4:H$1000) -> 0 | H57: =SUMIF('T12 Intake'!$Q$4:$Q$1000,$B57,'T12 Intake'!I$4:I$1000) -> 0 | I57: =SUMIF('T12 Intake'!$Q$4:$Q$1000,$B57,'T12 Intake'!J$4:J$1000) -> 0 | J57: =SUMIF('T12 Intake'!$Q$4:$Q$1000,$B57,'T12 Intake'!K$4:K$1000) -> 0 | ... O57: =SUMIF('T12 Intake'!$Q$4:$Q$1000,$B57,'T12 Intake'!P$4:P$1000) -> 0
B58: Net Operating Cash Flow (match Seller's #s) | C58: =C55+C56-C57 -> 0 | D58: =D55+D56-D57 -> 0 | E58: =E55+E56-E57 -> 0 | F58: =F55+F56-F57 -> 0 | G58: =G55+G56-G57 -> 0 | H58: =H55+H56-H57 -> 0 | I58: =I55+I56-I57 -> 0 | J58: =J55+J56-J57 -> 0 | ... O58: =O55+O56-O57 -> 0
O59: =O58-'T12 Intake'!$S$40 -> 0
O60: =IF(ROUND(O59,3)=0,"MATCH","REVIEW") -> MATCH

Sheet T12 Intake
B2: =CONCATENATE('QuickVal Proforma'!C5," | ","T12 Intake") -> | T12 Intake
B3: Code | C3: Line Item Months ---> | D3: =EOMONTH(E3,-1) -> 45535 | E3: =EOMONTH(F3,-1) -> 45565 | F3: =EOMONTH(G3,-1) -> 45596 | G3: =EOMONTH(H3,-1) -> 45626 | H3: =EOMONTH(I3,-1) -> 45657 | I3: =EOMONTH(J3,-1) -> 45688 | J3: =EOMONTH(K3,-1) -> 45716 | K3: =EOMONTH(L3,-1) -> 45747 | ... N3: =EOMONTH(O3,-1) -> 45838 | O3: 45869 | P3: TOTALS | Q3: ¯¯ Select Mesirow COA Code ¯¯ | S3: Coding Dictionary | T3: Shortcuts
S4: Gross Potential Rent - Market Rate | T4: mkt
S5: Gross Potential Rent - Affordables | T5: aff
S6: Gain / Loss-to-Lease | T6: ltl
S7: Physical Vacancy | T7: vac
S8: Concessions | T8: conc
S9: Employee / Model Units | T9: empmo
S10: Down Units | T10: down
S11: Bad Debt / Write-Offs | T11: bd
S12: Parking | T12: pkg
S13: Storage | T13: stg
S14: Pet Fees / Rent | T14: pet
S15: Cable / Internet | T15: tv
... S37: N/A Expenses / Entity Expenses | T37: nae
S39: Input Seller's NOI for Check
